Workbook

Sheet Painel
B2: RADAR LOW TICKET — ofertas mineradas
B4: Base: vault Obsidian /lowticket — 123 registros (103 ofertas + 20 angulos). iGreen fora. Notas recalculam sozinhas se voce editar a aba Ofertas.
B6: Registros | D6: Quentes (nota >= 7) | F6: Escalaveis (>= 7) | H6: Potencial Alta | J6: Rodando agora | L6: Veredito replicar | N6: Criativos ativos | P6: Ticket medio (R$)
B7: =COUNTA(Ofertas!A2:A124) -> 123 | D7: =COUNTIF(Ofertas!B2:B124,">=7") -> 12 | F7: =COUNTIF(Ofertas!C2:C124,">=7") -> 15 | H7: =COUNTIF(Ofertas!E2:E124,"Alta") -> 6 | J7: =COUNTIF(Ofertas!N2:N124,"ativa") -> 9 | L7: =COUNTIF(Ofertas!O2:O124,"replicar") -> 14 | N7: =SUM(Ofertas!L2:L124) -> 100 | P7: =ROUND(AVERAGEIF(Ofertas!S2:S124,">0"),0) -> 72
B10: TOP 12 — maior nota geral
B11: # | C11: Oferta | D11: Quente | E11: Escalavel | F11: Nota geral | G11: Potencial | H11: Criativos | I11: Dias no ar | J11: Nicho | K11: Pagina
B12: 1 | C12: Danca dos Noivos Online | D12: =INDEX(Ofertas!B:B,MATCH($C12,Ofertas!$A:$A,0)) -> 8.5 | E12: =INDEX(Ofertas!C:C,MATCH($C12,Ofertas!$A:$A,0)) -> 6.7 | F12: =INDEX(Ofertas!D:D,MATCH($C12,Ofertas!$A:$A,0)) -> 7.5 | G12: =INDEX(Ofertas!E:E,MATCH($C12,Ofertas!$A:$A,0)) -> Alta | H12: =INDEX(Ofertas!L:L,MATCH($C12,Ofertas!$A:$A,0)) -> 9 | I12: =INDEX(Ofertas!M:M,MATCH($C12,Ofertas!$A:$A,0)) -> 509 | J12: =INDEX(Ofertas!P:P,MATCH($C12,Ofertas!$A:$A,0)) -> danca | K12: abrir
B13: 2 | C13: +150 Bonecas de Papel — Maria Criativa | D13: =INDEX(Ofertas!B:B,MATCH($C13,Ofertas!$A:$A,0)) -> 8 | E13: =INDEX(Ofertas!C:C,MATCH($C13,Ofertas!$A:$A,0)) -> 6.9 | F13: =INDEX(Ofertas!D:D,MATCH($C13,Ofertas!$A:$A,0)) -> 7.4 | G13: =INDEX(Ofertas!E:E,MATCH($C13,Ofertas!$A:$A,0)) -> Alta | H13: =INDEX(Ofertas!L:L,MATCH($C13,Ofertas!$A:$A,0)) -> 9 | I13: =INDEX(Ofertas!M:M,MATCH($C13,Ofertas!$A:$A,0)) -> 54 | J13: =INDEX(Ofertas!P:P,MATCH($C13,Ofertas!$A:$A,0)) -> comportamento-infantil | K13: abrir
B14: 3 | C14: Retrato da Alma Gemea | D14: =INDEX(Ofertas!B:B,MATCH($C14,Ofertas!$A:$A,0)) -> 8 | E14: =INDEX(Ofertas!C:C,MATCH($C14,Ofertas!$A:$A,0)) -> 6.5 | F14: =INDEX(Ofertas!D:D,MATCH($C14,Ofertas!$A:$A,0)) -> 7.2 | G14: =INDEX(Ofertas!E:E,MATCH($C14,Ofertas!$A:$A,0)) -> Alta | H14: =INDEX(Ofertas!L:L,MATCH($C14,Ofertas!$A:$A,0)) -> 0 | I14: =INDEX(Ofertas!M:M,MATCH($C14,Ofertas!$A:$A,0)) -> 1826 | J14: =INDEX(Ofertas!P:P,MATCH($C14,Ofertas!$A:$A,0)) -> esoterico | K14: abrir
B15: 4 | C15: Colecao Completa de Caligrafia 1o ao 6o ano — 380 atividades | D15: =INDEX(Ofertas!B:B,MATCH($C15,Ofertas!$A:$A,0)) -> 7.5 | E15: =INDEX(Ofertas!C:C,MATCH($C15,Ofertas!$A:$A,0)) -> 6.8 | F15: =INDEX(Ofertas!D:D,MATCH($C15,Ofertas!$A:$A,0)) -> 7.1 | G15: =INDEX(Ofertas!E:E,MATCH($C15,Ofertas!$A:$A,0)) -> Alta | H15: =INDEX(Ofertas!L:L,MATCH($C15,Ofertas!$A:$A,0)) -> 8 | I15: =INDEX(Ofertas!M:M,MATCH($C15,Ofertas!$A:$A,0)) -> 123 | J15: =INDEX(Ofertas!P:P,MATCH($C15,Ofertas!$A:$A,0)) -> material-pedagogico | K15: abrir
B16: 5 | C16: Little Genius — Kit de 235+ atividades educativas | D16: =INDEX(Ofertas!B:B,MATCH($C16,Ofertas!$A:$A,0)) -> 6.5 | E16: =INDEX(Ofertas!C:C,MATCH($C16,Ofertas!$A:$A,0)) -> 7.5 | F16: =INDEX(Ofertas!D:D,MATCH($C16,Ofertas!$A:$A,0)) -> 7.1 | G16: =INDEX(Ofertas!E:E,MATCH($C16,Ofertas!$A:$A,0)) -> Alta | H16: =INDEX(Ofertas!L:L,MATCH($C16,Ofertas!$A:$A,0)) -> 1 | I16: =INDEX(Ofertas!M:M,MATCH($C16,Ofertas!$A:$A,0)) -> 76 | J16: =INDEX(Ofertas!P:P,MATCH($C16,Ofertas!$A:$A,0)) -> material-pedagogico | K16: abrir
B17: 6 | C17: Kit Grafismo Fonetico — Leitura Facil | D17: =INDEX(Ofertas!B:B,MATCH($C17,Ofertas!$A:$A,0)) -> 8 | E17: =INDEX(Ofertas!C:C,MATCH($C17,Ofertas!$A:$A,0)) -> 6.1 | F17: =INDEX(Ofertas!D:D,MATCH($C17,Ofertas!$A:$A,0)) -> 7 | G17: =INDEX(Ofertas!E:E,MATCH($C17,Ofertas!$A:$A,0)) -> Alta | H17: =INDEX(Ofertas!L:L,MATCH($C17,Ofertas!$A:$A,0)) -> 10 | I17: =INDEX(Ofertas!M:M,MATCH($C17,Ofertas!$A:$A,0)) -> 39 | J17: =INDEX(Ofertas!P:P,MATCH($C17,Ofertas!$A:$A,0)) -> material-pedagogico | K17: —
B18: 7 | C18: Missa em Atividades — kit catolico infantil imprimivel | D18: =INDEX(Ofertas!B:B,MATCH($C18,Ofertas!$A:$A,0)) -> 7 | E18: =INDEX(Ofertas!C:C,MATCH($C18,Ofertas!$A:$A,0)) -> 6.7 | F18: =INDEX(Ofertas!D:D,MATCH($C18,Ofertas!$A:$A,0)) -> 6.8 | G18: =INDEX(Ofertas!E:E,MATCH($C18,Ofertas!$A:$A,0)) -> Media | H18: =INDEX(Ofertas!L:L,MATCH($C18,Ofertas!$A:$A,0)) -> 3 | I18: =INDEX(Ofertas!M:M,MATCH($C18,Ofertas!$A:$A,0)) -> 35 | J18: =INDEX(Ofertas!P:P,MATCH($C18,Ofertas!$A:$A,0)) -> comportamento-infantil | K18: —
B19: 8 | C19: Cantigas da Bailarina — repertorio pronto para Baby Class | D19: =INDEX(Ofertas!B:B,MATCH($C19,Ofertas!$A:$A,0)) -> 7 | E19: =INDEX(Ofertas!C:C,MATCH($C19,Ofertas!$A:$A,0)) -> 6.2 | F19: =INDEX(Ofertas!D:D,MATCH($C19,Ofertas!$A:$A,0)) -> 6.6 | G19: =INDEX(Ofertas!E:E,MATCH($C19,Ofertas!$A:$A,0)) -> Media | H19: =INDEX(Ofertas!L:L,MATCH($C19,Ofertas!$A:$A,0)) -> 11 | I19: =INDEX(Ofertas!M:M,MATCH($C19,Ofertas!$A:$A,0)) -> 9 | J19: =INDEX(Ofertas!P:P,MATCH($C19,Ofertas!$A:$A,0)) -> danca | K19: abrir
B20: 9 | C20: Angulo — material pronto para quem ENSINA danca | D20: =INDEX(Ofertas!B:B,MATCH($C20,Ofertas!$A:$A,0)) -> 7 | E20: =INDEX(Ofertas!C:C,MATCH($C20,Ofertas!$A:$A,0)) -> 6.2 | F20: =INDEX(Ofertas!D:D,MATCH($C20,Ofertas!$A:$A,0)) -> 6.6 | G20: =INDEX(Ofertas!E:E,MATCH($C20,Ofertas!$A:$A,0)) -> Media | H20: =INDEX(Ofertas!L:L,MATCH($C20,Ofertas!$A:$A,0)) -> 19 | I20: =INDEX(Ofertas!M:M,MATCH($C20,Ofertas!$A:$A,0)) -> 10 | J20: =INDEX(Ofertas!P:P,MATCH($C20,Ofertas!$A:$A,0)) -> danca | K20: —
B21: 10 | C21: Casinha dos Sonhos — casinha de papel imprimivel | D21: =INDEX(Ofertas!B:B,MATCH($C21,Ofertas!$A:$A,0)) -> 6 | E21: =INDEX(Ofertas!C:C,MATCH($C21,Ofertas!$A:$A,0)) -> 6.9 | F21: =INDEX(Ofertas!D:D,MATCH($C21,Ofertas!$A:$A,0)) -> 6.5 | G21: =INDEX(Ofertas!E:E,MATCH($C21,Ofertas!$A:$A,0)) -> Media | H21: =INDEX(Ofertas!L:L,MATCH($C21,Ofertas!$A:$A,0)) -> 2 | I21: =INDEX(Ofertas!M:M,MATCH($C21,Ofertas!$A:$A,0)) -> 42 | J21: =INDEX(Ofertas!P:P,MATCH($C21,Ofertas!$A:$A,0)) -> comportamento-infantil | K21: abrir
B22: 11 | C22: Kit de Alfabetizacao Alfa Kids — 2.750 atividades | D22: =INDEX(Ofertas!B:B,MATCH($C22,Ofertas!$A:$A,0)) -> 6.5 | E22: =INDEX(Ofertas!C:C,MATCH($C22,Ofertas!$A:$A,0)) -> 6.1 | F22: =INDEX(Ofertas!D:D,MATCH($C22,Ofertas!$A:$A,0)) -> 6.3 | G22: =INDEX(Ofertas!E:E,MATCH($C22,Ofertas!$A:$A,0)) -> Media | H22: =INDEX(Ofertas!L:L,MATCH($C22,Ofertas!$A:$A,0)) -> 2 | I22: =INDEX(Ofertas!M:M,MATCH($C22,Ofertas!$A:$A,0)) -> 107 | J22: =INDEX(Ofertas!P:P,MATCH($C22,Ofertas!$A:$A,0)) -> material-pedagogico | K22: —
B23: 12 | C23: Clube da Pedagogia — kit 3.000+ atividades BNCC | D23: =INDEX(Ofertas!B:B,MATCH($C23,Ofertas!$A:$A,0)) -> 6.5 | E23: =INDEX(Ofertas!C:C,MATCH($C23,Ofertas!$A:$A,0)) -> 6.1 | F23: =INDEX(Ofertas!D:D,MATCH($C23,Ofertas!$A:$A,0)) -> 6.3 | G23: =INDEX(Ofertas!E:E,MATCH($C23,Ofertas!$A:$A,0)) -> Media | H23: =INDEX(Ofertas!L:L,MATCH($C23,Ofertas!$A:$A,0)) -> 1 | I23: =INDEX(Ofertas!M:M,MATCH($C23,Ofertas!$A:$A,0)) -> 74 | J23: =INDEX(Ofertas!P:P,MATCH($C23,Ofertas!$A:$A,0)) -> material-pedagogico | K23: abrir
B26: Nichos — onde o dinheiro aparece | J26: Como as notas sao calculadas
B27: Nicho | C27: Ofertas | D27: Nota media | E27: Quente media | F27: Criativos ativos | G27: Ticket medio (R$) | H27: Barra
B28: comportamento-infantil | C28: =COUNTIF(Ofertas!$P$2:$P$124,$B28) -> 23 | D28: =IFERROR(ROUND(AVERAGEIF(Ofertas!$P$2:$P$124,$B28,Ofertas!$D$2:$D$124),1),"") -> 4.4 | E28: =IFERROR(ROUND(AVERAGEIF(Ofertas!$P$2:$P$124,$B28,Ofertas!$B$2:$B$124),1),"") -> 1.7 | F28: =SUMIF(Ofertas!$P$2:$P$124,$B28,Ofertas!$L$2:$L$124) -> 17 | G28: =IFERROR(ROUND(AVERAGEIF(Ofertas!$P$2:$P$124,$B28,Ofertas!$S$2:$S$124),0),"") -> 34 | H28: =REPT("|",C28) -> ||||||||||||||||||||||| | J28: QUENTE (0-10) = prova de que esta rodando agora
B29: danca | C29: =COUNTIF(Ofertas!$P$2:$P$124,$B29) -> 13 | D29: =IFERROR(ROUND(AVERAGEIF(Ofertas!$P$2:$P$124,$B29,Ofertas!$D$2:$D$124),1),"") -> 5.8 | E29: =IFERROR(ROUND(AVERAGEIF(Ofertas!$P$2:$P$124,$B29,Ofertas!$B$2:$B$124),1),"") -> 6.2 | F29: =SUMIF(Ofertas!$P$2:$P$124,$B29,Ofertas!$L$2:$L$124) -> 58 | G29: =IFERROR(ROUND(AVERAGEIF(Ofertas!$P$2:$P$124,$B29,Ofertas!$S$2:$S$124),0),"") -> 109 | H29: =REPT("|",C29) -> ||||||||||||| | J29: status (ativa 5 / nova 4 / esfriando 2 / morta 0)
B30: material-pedagogico | C30: =COUNTIF(Ofertas!$P$2:$P$124,$B30) -> 11 | D30: =IFERROR(ROUND(AVERAGEIF(Ofertas!$P$2:$P$124,$B30,Ofertas!$D$2:$D$124),1),"") -> 6.1 | E30: =IFERROR(ROUND(AVERAGEIF(Ofertas!$P$2:$P$124,$B30,Ofertas!$B$2:$B$124),1),"") -> 5.8 | F30: =SUMIF(Ofertas!$P$2:$P$124,$B30,Ofertas!$L$2:$L$124) -> 25 | G30: =IFERROR(ROUND(AVERAGEIF(Ofertas!$P$2:$P$124,$B30,Ofertas!$S$2:$S$124),0),"") -> 27 | H30: =REPT("|",C30) -> ||||||||||| | J30: + criativos ativos (>=9 vale 3, >=3 vale 2, >=1 vale 1)
B31: religioso | C31: =COUNTIF(Ofertas!$P$2:$P$124,$B31) -> 11 | D31: =IFERROR(ROUND(AVERAGEIF(Ofertas!$P$2:$P$124,$B31,Ofertas!$D$2:$D$124),1),"") -> 3.8 | E31: =IFERROR(ROUND(AVERAGEIF(Ofertas!$P$2:$P$124,$B31,Ofertas!$B$2:$B$124),1),"") -> 0.2 | F31: =SUMIF(Ofertas!$P$2:$P$124,$B31,Ofertas!$L$2:$L$124) -> 0 | G31: =IFERROR(ROUND(AVERAGEIF(Ofertas!$P$2:$P$124,$B31,Ofertas!$S$2:$S$124),0),"") -> 98 | H31: =REPT("|",C31) -> ||||||||||| | J31: + tempo no ar (>=60d 1,5 / >=30d 1 / >=14d 0,5)
B32: ganhar-dinheiro | C32: =COUNTIF(Ofertas!$P$2:$P$124,$B32) -> 7 | D32: =IFERROR(ROUND(AVERAGEIF(Ofertas!$P$2:$P$124,$B32,Ofertas!$D$2:$D$124),1),"") -> 4 | E32: =IFERROR(ROUND(AVERAGEIF(Ofertas!$P$2:$P$124,$B32,Ofertas!$B$2:$B$124),1),"") -> 3.4 | F32: =SUMIF(Ofertas!$P$2:$P$124,$B32,Ofertas!$L$2:$L$124) -> 0 | G32: =IFERROR(ROUND(AVERAGEIF(Ofertas!$P$2:$P$124,$B32,Ofertas!$S$2:$S$124),0),"") -> 91 | H32: =REPT("|",C32) -> ||||||| | J32: + reclamacoes no ReclameAqui (>=50 1,5 / >=10 1 / >=1 0,5)
B33: esoterico | C33: =COUNTIF(Ofertas!$P$2:$P$124,$B33) -> 4 | D33: =IFERROR(ROUND(AVERAGEIF(Ofertas!$P$2:$P$124,$B33,Ofertas!$D$2:$D$124),1),"") -> 5.7 | E33: =IFERROR(ROUND(AVERAGEIF(Ofertas!$P$2:$P$124,$B33,Ofertas!$B$2:$B$124),1),"") -> 4.9 | F33: =SUMIF(Ofertas!$P$2:$P$124,$B33,Ofertas!$L$2:$L$124) -> 0 | G33: =IFERROR(ROUND(AVERAGEIF(Ofertas!$P$2:$P$124,$B33,Ofertas!$S$2:$S$124),0),"") -> 18 | H33: =REPT("|",C33) -> |||| | J33: + apareceu em 4+ rodadas (0,5)
B34: certificacao | C34: =COUNTIF(Ofertas!$P$2:$P$124,$B34) -> 4 | D34: =IFERROR(ROUND(AVERAGEIF(Ofertas!$P$2:$P$124,$B34,Ofertas!$D$2:$D$124),1),"") -> 5.6 | E34: =IFERROR(ROUND(AVERAGEIF(Ofertas!$P$2:$P$124,$B34,Ofertas!$B$2:$B$124),1),"") -> 6.1 | F34: =SUMIF(Ofertas!$P$2:$P$124,$B34,Ofertas!$L$2:$L$124) -> 0 | G34: =IFERROR(ROUND(AVERAGEIF(Ofertas!$P$2:$P$124,$B34,Ofertas!$S$2:$S$124),0),"") -> 92 | H34: =REPT("|",C34) -> ||||
B35: renda-celular-cashback | C35: =COUNTIF(Ofertas!$P$2:$P$124,$B35) -> 4 | D35: =IFERROR(ROUND(AVERAGEIF(Ofertas!$P$2:$P$124,$B35,Ofertas!$D$2:$D$124),1),"") -> 2.6 | E35: =IFERROR(ROUND(AVERAGEIF(Ofertas!$P$2:$P$124,$B35,Ofertas!$B$2:$B$124),1),"") -> 1 | F35: =SUMIF(Ofertas!$P$2:$P$124,$B35,Ofertas!$L$2:$L$124) -> 0 | G35: =IFERROR(ROUND(AVERAGEIF(Ofertas!$P$2:$P$124,$B35,Ofertas!$S$2:$S$124),0),"") -> 66 | H35: =REPT("|",C35) -> |||| | J35: ESCALAVEL (0-10) = quanto voce consegue refazer e lucrar
B36: saude-estetica-fitness | C36: =COUNTIF(Ofertas!$P$2:$P$124,$B36) -> 3 | D36: =IFERROR(ROUND(AVERAGEIF(Ofertas!$P$2:$P$124,$B36,Ofertas!$D$2:$D$124),1),"") -> 4.1 | E36: =IFERROR(ROUND(AVERAGEIF(Ofertas!$P$2:$P$124,$B36,Ofertas!$B$2:$B$124),1),"") -> 2.7 | F36: =SUMIF(Ofertas!$P$2:$P$124,$B36,Ofertas!$L$2:$L$124) -> 0 | G36: =IFERROR(ROUND(AVERAGEIF(Ofertas!$P$2:$P$124,$B36,Ofertas!$S$2:$S$124),0),"") -> 115 | H36: =REPT("|",C36) -> ||| | J36: s_replica x0,40 + s_lucro x0,25 + s_saturacao x0,20 + s_ticket x0,15
B37: ia-ferramentas | C37: =COUNTIF(Ofertas!$P$2:$P$124,$B37) -> 3 | D37: =IFERROR(ROUND(AVERAGEIF(Ofertas!$P$2:$P$124,$B37,Ofertas!$D$2:$D$124),1),"") -> 3.7 | E37: =IFERROR(ROUND(AVERAGEIF(Ofertas!$P$2:$P$124,$B37,Ofertas!$B$2:$B$124),1),"") -> 3 | F37: =SUMIF(Ofertas!$P$2:$P$124,$B37,Ofertas!$L$2:$L$124) -> 0 | G37: =IFERROR(ROUND(AVERAGEIF(Ofertas!$P$2:$P$124,$B37,Ofertas!$S$2:$S$124),0),"") -> 38 | H37: =REPT("|",C37) -> |||
B38: educacao | C38: =COUNTIF(Ofertas!$P$2:$P$124,$B38) -> 3 | D38: =IFERROR(ROUND(AVERAGEIF(Ofertas!$P$2:$P$124,$B38,Ofertas!$D$2:$D$124),1),"") -> 3.6 | E38: =IFERROR(ROUND(AVERAGEIF(Ofertas!$P$2:$P$124,$B38,Ofertas!$B$2:$B$124),1),"") -> 0 | F38: =SUMIF(Ofertas!$P$2:$P$124,$B38,Ofertas!$L$2:$L$124) -> 0 | G38: =IFERROR(ROUND(AVERAGEIF(Ofertas!$P$2:$P$124,$B38,Ofertas!$S$2:$S$124),0),"") -> 26 | H38: =REPT("|",C38) -> ||| | J38: NOTA GERAL = Quente x0,45 + Escalavel x0,55
B39: concursos | C39: =COUNTIF(Ofertas!$P$2:$P$124,$B39) -> 3 | D39: =IFERROR(ROUND(AVERAGEIF(Ofertas!$P$2:$P$124,$B39,Ofertas!$D$2:$D$124),1),"") -> 3.4 | E39: =IFERROR(ROUND(AVERAGEIF(Ofertas!$P$2:$P$124,$B39,Ofertas!$B$2:$B$124),1),"") -> 0.3 | F39: =SUMIF(Ofertas!$P$2:$P$124,$B39,Ofertas!$L$2:$L$124) -> 0 | G39: =IFERROR(ROUND(AVERAGEIF(Ofertas!$P$2:$P$124,$B39,Ofertas!$S$2:$S$124),0),"") -> 38 | H39: =REPT("|",C39) -> ||| | J39: Potencial: Alta >= 7 | Media >= 5 | Baixa < 5
B40: servicos-empresariais | C40: =COUNTIF(Ofertas!$P$2:$P$124,$B40) -> 2 | D40: =IFERROR(ROUND(AVERAGEIF(Ofertas!$P$2:$P$124,$B40,Ofertas!$D$2:$D$124),1),"") -> 5.4 | E40: =IFERROR(ROUND(AVERAGEIF(Ofertas!$P$2:$P$124,$B40,Ofertas!$B$2:$B$124),1),"") -> 6.3 | F40: =SUMIF(Ofertas!$P$2:$P$124,$B40,Ofertas!$L$2:$L$124) -> 0 | G40: =IFERROR(ROUND(AVERAGEIF(Ofertas!$P$2:$P$124,$B40,Ofertas!$S$2:$S$124),0),"") -> 0 | H40: =REPT("|",C40) -> ||
B41: artesanato-e-pdf | C41: =COUNTIF(Ofertas!$P$2:$P$124,$B41) -> 2 | D41: =IFERROR(ROUND(AVERAGEIF(Ofertas!$P$2:$P$124,$B41,Ofertas!$D$2:$D$124),1),"") -> 4.8 | E41: =IFERROR(ROUND(AVERAGEIF(Ofertas!$P$2:$P$124,$B41,Ofertas!$B$2:$B$124),1),"") -> 1.8 | F41: =SUMIF(Ofertas!$P$2:$P$124,$B41,Ofertas!$L$2:$L$124) -> 0 | G41: =IFERROR(ROUND(AVERAGEIF(Ofertas!$P$2:$P$124,$B41,Ofertas!$S$2:$S$124),0),"") -> 28 | H41: =REPT("|",C41) -> || | J41: Linha roxa na aba Ofertas = mesma pagina de destino que outra oferta.
B42: espionagem-rastreamento | C42: =COUNTIF(Ofertas!$P$2:$P$124,$B42) -> 2 | D42: =IFERROR(ROUND(AVERAGEIF(Ofertas!$P$2:$P$124,$B42,Ofertas!$D$2:$D$124),1),"") -> 3.6 | E42: =IFERROR(ROUND(AVERAGEIF(Ofertas!$P$2:$P$124,$B42,Ofertas!$B$2:$B$124),1),"") -> 1.8 | F42: =SUMIF(Ofertas!$P$2:$P$124,$B42,Ofertas!$L$2:$L$124) -> 0 | G42: =IFERROR(ROUND(AVERAGEIF(Ofertas!$P$2:$P$124,$B42,Ofertas!$S$2:$S$124),0),"") -> 86 | H42: =REPT("|",C42) -> ||
B43: streaming-e-acesso | C43: =COUNTIF(Ofertas!$P$2:$P$124,$B43) -> 2 | D43: =IFERROR(ROUND(AVERAGEIF(Ofertas!$P$2:$P$124,$B43,Ofertas!$D$2:$D$124),1),"") -> 3.3 | E43: =IFERROR(ROUND(AVERAGEIF(Ofertas!$P$2:$P$124,$B43,Ofertas!$B$2:$B$124),1),"") -> 1.8 | F43: =SUMIF(Ofertas!$P$2:$P$124,$B43,Ofertas!$L$2:$L$124) -> 0 | G43: =IFERROR(ROUND(AVERAGEIF(Ofertas!$P$2:$P$124,$B43,Ofertas!$S$2:$S$124),0),"") -> 20 | H43: =REPT("|",C43) -> ||
B44: marketing-digital | C44: =COUNTIF(Ofertas!$P$2:$P$124,$B44) -> 2 | D44: =IFERROR(ROUND(AVERAGEIF(Ofertas!$P$2:$P$124,$B44,Ofertas!$D$2:$D$124),1),"") -> 3.8 | E44: =IFERROR(ROUND(AVERAGEIF(Ofertas!$P$2:$P$124,$B44,Ofertas!$B$2:$B$124),1),"") -> 1.5 | F44: =SUMIF(Ofertas!$P$2:$P$124,$B44,Ofertas!$L$2:$L$124) -> 0 | G44: =IFERROR(ROUND(AVERAGEIF(Ofertas!$P$2:$P$124,$B44,Ofertas!$S$2:$S$124),0),"") -> 180 | H44: =REPT("|",C44) -> ||
B45: lives-interativas | C45: =COUNTIF(Ofertas!$P$2:$P$124,$B45) -> 2 | D45: =IFERROR(ROUND(AVERAGEIF(Ofertas!$P$2:$P$124,$B45,Ofertas!$D$2:$D$124),1),"") -> 3.3 | E45: =IFERROR(ROUND(AVERAGEIF(Ofertas!$P$2:$P$124,$B45,Ofertas!$B$2:$B$124),1),"") -> 1.5 | F45: =SUMIF(Ofertas!$P$2:$P$124,$B45,Ofertas!$L$2:$L$124) -> 0 | G45: =IFERROR(ROUND(AVERAGEIF(Ofertas!$P$2:$P$124,$B45,Ofertas!$S$2:$S$124),0),"") -> 75 | H45: =REPT("|",C45) -> ||
B46: ferramentas-ia | C46: =COUNTIF(Ofertas!$P$2:$P$124,$B46) -> 2 | D46: =IFERROR(ROUND(AVERAGEIF(Ofertas!$P$2:$P$124,$B46,Ofertas!$D$2:$D$124),1),"") -> 3.3 | E46: =IFERROR(ROUND(AVERAGEIF(Ofertas!$P$2:$P$124,$B46,Ofertas!$B$2:$B$124),1),"") -> 0.5 | F46: =SUMIF(Ofertas!$P$2:$P$124,$B46,Ofertas!$L$2:$L$124) -> 0 | G46: =IFERROR(ROUND(AVERAGEIF(Ofertas!$P$2:$P$124,$B46,Ofertas!$S$2:$S$124),0),"") -> 74 | H46: =REPT("|",C46) -> ||
B47: emagrecimento | C47: =COUNTIF(Ofertas!$P$2:$P$124,$B47) -> 2 | D47: =IFERROR(ROUND(AVERAGEIF(Ofertas!$P$2:$P$124,$B47,Ofertas!$D$2:$D$124),1),"") -> 2.9 | E47: =IFERROR(ROUND(AVERAGEIF(Ofertas!$P$2:$P$124,$B47,Ofertas!$B$2:$B$124),1),"") -> 0.5 | F47: =SUMIF(Ofertas!$P$2:$P$124,$B47,Ofertas!$L$2:$L$124) -> 0 | G47: =IFERROR(ROUND(AVERAGEIF(Ofertas!$P$2:$P$124,$B47,Ofertas!$S$2:$S$124),0),"") -> 53 | H47: =REPT("|",C47) -> ||
B48: mecanica-de-checkout | C48: =COUNTIF(Ofertas!$P$2:$P$124,$B48) -> 1 | D48: =IFERROR(ROUND(AVERAGEIF(Ofertas!$P$2:$P$124,$B48,Ofertas!$D$2:$D$124),1),"") -> 5.8 | E48: =IFERROR(ROUND(AVERAGEIF(Ofertas!$P$2:$P$124,$B48,Ofertas!$B$2:$B$124),1),"") -> 5.5 | F48: =SUMIF(Ofertas!$P$2:$P$124,$B48,Ofertas!$L$2:$L$124) -> 0 | G48: =IFERROR(ROUND(AVERAGEIF(Ofertas!$P$2:$P$124,$B48,Ofertas!$S$2:$S$124),0),"") -> 47 | H48: =REPT("|",C48) -> |
B49: musica-producao | C49: =COUNTIF(Ofertas!$P$2:$P$124,$B49) -> 1 | D49: =IFERROR(ROUND(AVERAGEIF(Ofertas!$P$2:$P$124,$B49,Ofertas!$D$2:$D$124),1),"") -> 4.9 | E49: =IFERROR(ROUND(AVERAGEIF(Ofertas!$P$2:$P$124,$B49,Ofertas!$B$2:$B$124),1),"") -> 3 | F49: =SUMIF(Ofertas!$P$2:$P$124,$B49,Ofertas!$L$2:$L$124) -> 0 | G49: =IFERROR(ROUND(AVERAGEIF(Ofertas!$P$2:$P$124,$B49,Ofertas!$S$2:$S$124),0),"") -> 40 | H49: =REPT("|",C49) -> |
B50: artesanato-digital | C50: =COUNTIF(Ofertas!$P$2:$P$124,$B50) -> 1 | D50: =IFERROR(ROUND(AVERAGEIF(Ofertas!$P$2:$P$124,$B50,Ofertas!$D$2:$D$124),1),"") -> 4.8 | E50: =IFERROR(ROUND(AVERAGEIF(Ofertas!$P$2:$P$124,$B50,Ofertas!$B$2:$B$124),1),"") -> 3 | F50: =SUMIF(Ofertas!$P$2:$P$124,$B50,Ofertas!$L$2:$L$124) -> 0 | G50: =IFERROR(ROUND(AVERAGEIF(Ofertas!$P$2:$P$124,$B50,Ofertas!$S$2:$S$124),0),"") -> 25 | H50: =REPT("|",C50) -> |
B51: sexualidade-bemestar | C51: =COUNTIF(Ofertas!$P$2:$P$124,$B51) -> 1 | D51: =IFERROR(ROUND(AVERAGEIF(Ofertas!$P$2:$P$124,$B51,Ofertas!$D$2:$D$124),1),"") -> 4.7 | E51: =IFERROR(ROUND(AVERAGEIF(Ofertas!$P$2:$P$124,$B51,Ofertas!$B$2:$B$124),1),"") -> 3 | F51: =SUMIF(Ofertas!$P$2:$P$124,$B51,Ofertas!$L$2:$L$124) -> 0 | G51: =IFERROR(ROUND(AVERAGEIF(Ofertas!$P$2:$P$124,$B51,Ofertas!$S$2:$S$124),0),"") -> 50 | H51: =REPT("|",C51) -> |
B52: idiomas | C52: =COUNTIF(Ofertas!$P$2:$P$124,$B52) -> 1 | D52: =IFERROR(ROUND(AVERAGEIF(Ofertas!$P$2:$P$124,$B52,Ofertas!$D$2:$D$124),1),"") -> 4.5 | E52: =IFERROR(ROUND(AVERAGEIF(Ofertas!$P$2:$P$124,$B52,Ofertas!$B$2:$B$124),1),"") -> 2.5 | F52: =SUMIF(Ofertas!$P$2:$P$124,$B52,Ofertas!$L$2:$L$124) -> 0 | G52: =IFERROR(ROUND(AVERAGEIF(Ofertas!$P$2:$P$124,$B52,Ofertas!$S$2:$S$124),0),"") -> 47 | H52: =REPT("|",C52) -> |
B53: imprimiveis-infantil | C53: =COUNTIF(Ofertas!$P$2:$P$124,$B53) -> 1 | D53: =IFERROR(ROUND(AVERAGEIF(Ofertas!$P$2:$P$124,$B53,Ofertas!$D$2:$D$124),1),"") -> 4.4 | E53: =IFERROR(ROUND(AVERAGEIF(Ofertas!$P$2:$P$124,$B53,Ofertas!$B$2:$B$124),1),"") -> 2 | F53: =SUMIF(Ofertas!$P$2:$P$124,$B53,Ofertas!$L$2:$L$124) -> 0 | G53: =IFERROR(ROUND(AVERAGEIF(Ofertas!$P$2:$P$124,$B53,Ofertas!$S$2:$S$124),0),"") -> 21 | H53: =REPT("|",C53) -> |
... B65: ferramentas-ia-edicao | C65: =COUNTIF(Ofertas!$P$2:$P$124,$B65) -> 1 | D65: =IFERROR(ROUND(AVERAGEIF(Ofertas!$P$2:$P$124,$B65,Ofertas!$D$2:$D$124),1),"") -> 2.2 | E65: =IFERROR(ROUND(AVERAGEIF(Ofertas!$P$2:$P$124,$B65,Ofertas!$B$2:$B$124),1),"") -> 2.5 | F65: =SUMIF(Ofertas!$P$2:$P$124,$B65,Ofertas!$L$2:$L$124) -> 0 | G65: =IFERROR(ROUND(AVERAGEIF(Ofertas!$P$2:$P$124,$B65,Ofertas!$S$2:$S$124),0),"") -> 0 | H65: =REPT("|",C65) -> |

Sheet Ofertas
A1: Nome da oferta | B1: Quente (0-10) | C1: Escalavel (0-10) | D1: Nota geral | E1: Possibilidade de escala | F1: Grupo (mesmo destino) | G1: Ofertas no destino | H1: Cluster (mesma oferta/angulo) | I1: Ofertas no cluster | J1: Pagina de vendas | K1: Criativo / Biblioteca de Anuncios | L1: Criativos ativos | M1: Dias no ar | N1: Status | O1: Veredito | P1: Nicho | Q1: Sub-nicho | R1: Ticket frente (R$) | S1: Ticket medio est. (R$) | T1: Margem est. | U1: Checkout | V1: Reclamacoes RA | W1: Rodadas vista | X1: Visto primeiro | Y1: Visto ultimo | Z1: Entrega | AA1: Recorrencia | AB1: Tipo | AC1: s_ticket | AD1: s_lucro | AE1: s_replica | AF1: s_saturacao | AG1: Anunciante | AH1: Resumo
A2: Danca dos Noivos Online | B2: =MIN(10, IF(N2="ativa",5,IF(N2="nova",4,IF(N2="esfriando",2,0)))+IF(L2>=9,3,IF(L2>=3,2,IF(L2>=1,1,0)))+IF(M2>=60,1.5,IF(M2>=30,1,IF(M2>=14,0.5,0)))+IF(V2>=50,1.5,IF(V2>=10,1,IF(V2>=1,0.5,0)))+IF(W2>=4,0.5,0)) -> 8.5 | C2: =ROUND(AC2*0.15+AD2*0.25+AE2*0.4+AF2*0.2,1) -> 6.7 | D2: =ROUND(B2*0.45+C2*0.55,1) -> 7.5 | E2: =IF(D2>=7,"Alta",IF(D2>=5,"Media","Baixa")) -> Alta | F2: dancadosnoivosonline.com | G2: 1 | H2: danca-dos-noivos | I2: 1 | J2: abrir pagina | K2: anuncio 9 criativo(s) | L2: 9 | M2: 509 | N2: nova | O2: observar | P2: danca | Q2: danca-dos-noivos | R2: 97 | S2: 150 | T2: 0.85 | U2: hotmart | V2: 0 | W2: 1 | X2: 2026-09-06 | Y2: 2026-09-06 | Z2: curso | AA2: nao | AB2: Oferta | AC2: 9 | AD2: 10 | AE2: 3 | AF2: 8 | AG2: Danca dos Noivos | AH2: # Danca dos Noivos Online
A3: +150 Bonecas de Papel — Maria Criativa | B3: =MIN(10, IF(N3="ativa",5,IF(N3="nova",4,IF(N3="esfriando",2,0)))+IF(L3>=9,3,IF(L3>=3,2,IF(L3>=1,1,0)))+IF(M3>=60,1.5,IF(M3>=30,1,IF(M3>=14,0.5,0)))+IF(V3>=50,1.5,IF(V3>=10,1,IF(V3>=1,0.5,0)))+IF(W3>=4,0.5,0)) -> 8 | C3: =ROUND(AC3*0.15+AD3*0.25+AE3*0.4+AF3*0.2,1) -> 6.9 | D3: =ROUND(B3*0.45+C3*0.55,1) -> 7.4 | E3: =IF(D3>=7,"Alta",IF(D3>=5,"Media","Baixa")) -> Alta | F3: bonecasdepapel28.lovable.app | G3: 1 | H3: imprimivel-brincadeira | I3: 4 | J3: abrir pagina | K3: buscar na biblioteca | L3: 9 | M3: 54 | N3: nova | O3: observar | P3: comportamento-infantil | Q3: imprimivel-brincadeira | R3: 17.9 | S3: 24 | T3: 0.9 | U3: kirvano | V3: 0 | W3: 1 | X3: 2026-08-31 | Y3: 2026-08-31 | Z3: ebook | AA3: nao | AB3: Oferta | AC3: 3 | AD3: 8 | AE3: 10 | AF3: 2 | AH3: # +150 Bonecas de Papel — Maria Criativa
A4: Retrato da Alma Gemea | B4: =MIN(10, IF(N4="ativa",5,IF(N4="nova",4,IF(N4="esfriando",2,0)))+IF(L4>=9,3,IF(L4>=3,2,IF(L4>=1,1,0)))+IF(M4>=60,1.5,IF(M4>=30,1,IF(M4>=14,0.5,0)))+IF(V4>=50,1.5,IF(V4>=10,1,IF(V4>=1,0.5,0)))+IF(W4>=4,0.5,0)) -> 8 | C4: =ROUND(AC4*0.15+AD4*0.25+AE4*0.4+AF4*0.2,1) -> 6.5 | D4: =ROUND(B4*0.45+C4*0.55,1) -> 7.2 | E4: =IF(D4>=7,"Alta",IF(D4>=5,"Media","Baixa")) -> Alta | F4: alldigital.fun | G4: 1 | H4: retrato-alma-gemea | I4: 3 | J4: abrir pagina | K4: buscar na biblioteca | L4: 0 | M4: 1826 | N4: ativa | O4: observar | P4: esoterico | Q4: retrato-alma-gemea | R4: 29 | S4: 45 | T4: 0.97 | U4: kirvano | V4: 206 | W4: 2 | X4: 2026-08-30 | Y4: 2026-08-31 | Z4: servico-digital | AA4: nao | AB4: Oferta | AC4: 3 | AD4: 8 | AE4: 9 | AF4: 2 | AH4: # Retrato da Alma Gemea
A5: Colecao Completa de Caligrafia 1o ao 6o ano — 380 atividades | B5: =MIN(10, IF(N5="ativa",5,IF(N5="nova",4,IF(N5="esfriando",2,0)))+IF(L5>=9,3,IF(L5>=3,2,IF(L5>=1,1,0)))+IF(M5>=60,1.5,IF(M5>=30,1,IF(M5>=14,0.5,0)))+IF(V5>=50,1.5,IF(V5>=10,1,IF(V5>=1,0.5,0)))+IF(W5>=4,0.5,0)) -> 7.5 | C5: =ROUND(AC5*0.15+AD5*0.25+AE5*0.4+AF5*0.2,1) -> 6.8 | D5: =ROUND(B5*0.45+C5*0.55,1) -> 7.1 | E5: =IF(D5>=7,"Alta",IF(D5>=5,"Media","Baixa")) -> Alta | F5: atividade-cursiva.netlify.app | G5: 1 | H5: caligrafia | I5: 4 | J5: abrir pagina | K5: buscar na biblioteca | L5: 8 | M5: 123 | N5: nova | O5: replicar | P5: material-pedagogico | Q5: caligrafia | R5: 12 | S5: 12 | T5: 0.9 | U5: cakto | V5: 0 | W5: 1 | X5: 2026-08-31 | Y5: 2026-08-31 | Z5: ebook | AA5: nao | AB5: Oferta | AC5: 2 | AD5: 9 | AE5: 9 | AF5: 3 | AH5: # Colecao Completa de Caligrafia — 380 atividades
A6: Little Genius — Kit de 235+ atividades educativas | B6: =MIN(10, IF(N6="ativa",5,IF(N6="nova",4,IF(N6="esfriando",2,0)))+IF(L6>=9,3,IF(L6>=3,2,IF(L6>=1,1,0)))+IF(M6>=60,1.5,IF(M6>=30,1,IF(M6>=14,0.5,0)))+IF(V6>=50,1.5,IF(V6>=10,1,IF(V6>=1,0.5,0)))+IF(W6>=4,0.5,0)) -> 6.5 | C6: =ROUND(AC6*0.15+AD6*0.25+AE6*0.4+AF6*0.2,1) -> 7.5 | D6: =ROUND(B6*0.45+C6*0.55,1) -> 7.1 | E6: =IF(D6>=7,"Alta",IF(D6>=5,"Media","Baixa")) -> Alta | F6: thelittlegenius.com.br | G6: 1 | H6: estimulacao-cognitiva | I6: 1 | J6: abrir pagina | K6: buscar na biblioteca | L6: 1 | M6: 76 | N6: nova | O6: observar | P6: material-pedagogico | Q6: estimulacao-cognitiva | R6: 162 | S6: 162 | T6: 0.85 | U6: kiwify | V6: 0 | W6: 1 | X6: 2026-08-31 | Y6: 2026-08-31 | Z6: ebook | AA6: nao | AB6: Oferta | AC6: 10 | AD6: 7 | AE6: 7 | AF6: 7 | AH6: # Little Genius — 235 atividades a R$ 162
A7: Kit Grafismo Fonetico — Leitura Facil | B7: =MIN(10, IF(N7="ativa",5,IF(N7="nova",4,IF(N7="esfriando",2,0)))+IF(L7>=9,3,IF(L7>=3,2,IF(L7>=1,1,0)))+IF(M7>=60,1.5,IF(M7>=30,1,IF(M7>=14,0.5,0)))+IF(V7>=50,1.5,IF(V7>=10,1,IF(V7>=1,0.5,0)))+IF(W7>=4,0.5,0)) -> 8 | C7: =ROUND(AC7*0.15+AD7*0.25+AE7*0.4+AF7*0.2,1) -> 6.1 | D7: =ROUND(B7*0.45+C7*0.55,1) -> 7 | E7: =IF(D7>=7,"Alta",IF(D7>=5,"Media","Baixa")) -> Alta | F7: busca: grafismo fonetico | G7: 1 | H7: alfabetizacao | I7: 4 | J7: — | K7: buscar na biblioteca | L7: 10 | M7: 39 | N7: nova | O7: observar | P7: material-pedagogico | Q7: alfabetizacao | R7: 20 | S7: 20 | T7: 0.9 | U7: whatsapp | V7: 0 | W7: 1 | X7: 2026-08-31 | Y7: 2026-08-31 | Z7: ebook | AA7: nao | AB7: Oferta | AC7: 2 | AD7: 7 | AE7: 8 | AF7: 4 | AH7: # Kit Grafismo Fonetico — venda por conversa, 10 criativos
A8: Missa em Atividades — kit catolico infantil imprimivel | B8: =MIN(10, IF(N8="ativa",5,IF(N8="nova",4,IF(N8="esfriando",2,0)))+IF(L8>=9,3,IF(L8>=3,2,IF(L8>=1,1,0)))+IF(M8>=60,1.5,IF(M8>=30,1,IF(M8>=14,0.5,0)))+IF(V8>=50,1.5,IF(V8>=10,1,IF(V8>=1,0.5,0)))+IF(W8>=4,0.5,0)) -> 7 | C8: =ROUND(AC8*0.15+AD8*0.25+AE8*0.4+AF8*0.2,1) -> 6.7 | D8: =ROUND(B8*0.45+C8*0.55,1) -> 6.8 | E8: =IF(D8>=7,"Alta",IF(D8>=5,"Media","Baixa")) -> Media | F8: busca: missa em atividades | G8: 1 | H8: catequese-infantil | I8: 1 | J8: — | K8: buscar na biblioteca | L8: 3 | M8: 35 | N8: nova | O8: replicar | P8: comportamento-infantil | Q8: catequese-infantil | R8: 0 | S8: 0 | T8: 0.9 | U8: desconhecido | V8: 0 | W8: 1 | X8: 2026-08-31 | Y8: 2026-08-31 | Z8: ebook | AA8: nao | AB8: Oferta | AC8: 0 | AD8: 5 | AE8: 9 | AF8: 9 | AH8: # Missa em Atividades — o cruzamento mais vazio do vault
A9: Cantigas da Bailarina — repertorio pronto para Baby Class | B9: =MIN(10, IF(N9="ativa",5,IF(N9="nova",4,IF(N9="esfriando",2,0)))+IF(L9>=9,3,IF(L9>=3,2,IF(L9>=1,1,0)))+IF(M9>=60,1.5,IF(M9>=30,1,IF(M9>=14,0.5,0)))+IF(V9>=50,1.5,IF(V9>=10,1,IF(V9>=1,0.5,0)))+IF(W9>=4,0.5,0)) -> 7 | C9: =ROUND(AC9*0.15+AD9*0.25+AE9*0.4+AF9*0.2,1) -> 6.2 | D9: =ROUND(B9*0.45+C9*0.55,1) -> 6.6 | E9: =IF(D9>=7,"Alta",IF(D9>=5,"Media","Baixa")) -> Media | F9: ballerinalab.com.br | G9: 1 | H9: material-para-professora-de-ballet | I9: 2 | J9: abrir pagina | K9: anuncio 11 criativo(s) | L9: 11 | M9: 9 | N9: nova | O9: observar | P9: danca | Q9: material-para-professora-de-ballet | R9: 19.9 | S9: 35 | T9: 0.9 | U9: ggcheckout | V9: 0 | W9: 1 | X9: 2026-09-06 | Y9: 2026-09-06 | Z9: ebook | AA9: nao | AB9: Oferta | AC9: 5 | AD9: 4 | AE9: 8 | AF9: 6 | AG9: Ballerina Lab | AH9: # Cantigas da Bailarina — Ballerina Lab
A10: Angulo — material pronto para quem ENSINA danca | B10: =MIN(10, IF(N10="ativa",5,IF(N10="nova",4,IF(N10="esfriando",2,0)))+IF(L10>=9,3,IF(L10>=3,2,IF(L10>=1,1,0)))+IF(M10>=60,1.5,IF(M10>=30,1,IF(M10>=14,0.5,0)))+IF(V10>=50,1.5,IF(V10>=10,1,IF(V10>=1,0.5,0)))+IF(W10>=4,0.5,0)) -> 7 | C10: =ROUND(AC10*0.15+AD10*0.25+AE10*0.4+AF10*0.2,1) -> 6.2 | D10: =ROUND(B10*0.45+C10*0.55,1) -> 6.6 | E10: =IF(D10>=7,"Alta",IF(D10>=5,"Media","Baixa")) -> Media | F10: busca: coreografias prontas | G10: 1 | H10: material-para-professor | I10: 1 | J10: — | K10: buscar na biblioteca | L10: 19 | M10: 10 | N10: nova | O10: replicar | P10: danca | Q10: material-para-professor | R10: 19.9 | S10: 30 | T10: 0.92 | U10: desconhecido | V10: 0 | W10: 1 | X10: 2026-09-06 | Y10: 2026-09-06 | Z10: ebook | AA10: nao | AB10: Angulo | AC10: 4 | AD10: 4 | AE10: 9 | AF10: 5 | AH10: # Angulo — material pronto para quem ENSINA danca
A11: Casinha dos Sonhos — casinha de papel imprimivel | B11: =MIN(10, IF(N11="ativa",5,IF(N11="nova",4,IF(N11="esfriando",2,0)))+IF(L11>=9,3,IF(L11>=3,2,IF(L11>=1,1,0)))+IF(M11>=60,1.5,IF(M11>=30,1,IF(M11>=14,0.5,0)))+IF(V11>=50,1.5,IF(V11>=10,1,IF(V11>=1,0.5,0)))+IF(W11>=4,0.5,0)) -> 6 | C11: =ROUND(AC11*0.15+AD11*0.25+AE11*0.4+AF11*0.2,1) -> 6.9 | D11: =ROUND(B11*0.45+C11*0.55,1) -> 6.5 | E11: =IF(D11>=7,"Alta",IF(D11>=5,"Media","Baixa")) -> Media | F11: casinhadossonhos.com.br | G11: 1 | H11: imprimivel-brincadeira | I11: 4 | J11: abrir pagina | K11: buscar na biblioteca | L11: 2 | M11: 42 | N11: nova | O11: observar | P11: comportamento-infantil | Q11: imprimivel-brincadeira | R11: 10 | S11: 10 | T11: 0.9 | U11: desconhecido | V11: 0 | W11: 1 | X11: 2026-08-31 | Y11: 2026-08-31 | Z11: ebook | AA11: nao | AB11: Oferta | AC11: 1 | AD11: 6 | AE11: 10 | AF11: 6 | AG11: Prof.a Juliana Gamon | AH11: # Casinha dos Sonhos — R$ 10, 42 dias no ar
A12: Kit de Alfabetizacao Alfa Kids — 2.750 atividades | B12: =MIN(10, IF(N12="ativa",5,IF(N12="nova",4,IF(N12="esfriando",2,0)))+IF(L12>=9,3,IF(L12>=3,2,IF(L12>=1,1,0)))+IF(M12>=60,1.5,IF(M12>=30,1,IF(M12>=14,0.5,0)))+IF(V12>=50,1.5,IF(V12>=10,1,IF(V12>=1,0.5,0)))+IF(W12>=4,0.5,0)) -> 6.5 | C12: =ROUND(AC12*0.15+AD12*0.25+AE12*0.4+AF12*0.2,1) -> 6.1 | D12: =ROUND(B12*0.45+C12*0.55,1) -> 6.3 | E12: =IF(D12>=7,"Alta",IF(D12>=5,"Media","Baixa")) -> Media | F12: busca: alfa kids | G12: 1 | H12: alfabetizacao | I12: 4 | J12: — | K12: buscar na biblioteca | L12: 2 | M12: 107 | N12: nova | O12: observar | P12: material-pedagogico | Q12: alfabetizacao | R12: 0 | S12: 0 | T12: 0.9 | U12: desconhecido | V12: 0 | W12: 1 | X12: 2026-08-31 | Y12: 2026-08-31 | Z12: ebook | AA12: nao | AB12: Oferta | AC12: 0 | AD12: 9 | AE12: 8 | AF12: 3 | AH12: # Turminha Alfa Kids — 107 dias no ar
A13: Clube da Pedagogia — kit 3.000+ atividades BNCC | B13: =MIN(10, IF(N13="ativa",5,IF(N13="nova",4,IF(N13="esfriando",2,0)))+IF(L13>=9,3,IF(L13>=3,2,IF(L13>=1,1,0)))+IF(M13>=60,1.5,IF(M13>=30,1,IF(M13>=14,0.5,0)))+IF(V13>=50,1.5,IF(V13>=10,1,IF(V13>=1,0.5,0)))+IF(W13>=4,0.5,0)) -> 6.5 | C13: =ROUND(AC13*0.15+AD13*0.25+AE13*0.4+AF13*0.2,1) -> 6.1 | D13: =ROUND(B13*0.45+C13*0.55,1) -> 6.3 | E13: =IF(D13>=7,"Alta",IF(D13>=5,"Media","Baixa")) -> Media | F13: clubedapedagogia.com | G13: 1 | H13: acervo-professora | I13: 2 | J13: abrir pagina | K13: buscar na biblioteca | L13: 1 | M13: 74 | N13: nova | O13: replicar | P13: material-pedagogico | Q13: acervo-professora | R13: 20 | S13: 35 | T13: 0.9 | U13: ggcheckout | V13: 0 | W13: 1 | X13: 2026-08-31 | Y13: 2026-08-31 | Z13: ebook | AA13: nao | AB13: Oferta | AC13: 5 | AD13: 7 | AE13: 7 | AF13: 4 | AH13: # Clube da Pedagogia — a escada que o cluster infantil nao tem
A14: Combo 10 Cursos de Danca do Ventre — Patricia Cavalcante | B14: =MIN(10, IF(N14="ativa",5,IF(N14="nova",4,IF(N14="esfriando",2,0)))+IF(L14>=9,3,IF(L14>=3,2,IF(L14>=1,1,0)))+IF(M14>=60,1.5,IF(M14>=30,1,IF(M14>=14,0.5,0)))+IF(V14>=50,1.5,IF(V14>=10,1,IF(V14>=1,0.5,0)))+IF(W14>=4,0.5,0)) -> 6.5 | C14: =ROUND(AC14*0.15+AD14*0.25+AE14*0.4+AF14*0.2,1) -> 6 | D14: =ROUND(B14*0.45+C14*0.55,1) -> 6.2 | E14: =IF(D14>=7,"Alta",IF(D14>=5,"Media","Baixa")) -> Media | F14: patriciacavalcante.com.br | G14: 1 | H14: danca-do-ventre | I14: 2 | J14: abrir pagina | K14: anuncio 2 criativo(s) | L14: 2 | M14: 584 | N14: nova | O14: descartar | P14: danca | Q14: danca-do-ventre | R14: 247 | S14: 247 | T14: 0.85 | U14: hotmart | V14: 0 | W14: 1 | X14: 2026-09-06 | Y14: 2026-09-06 | Z14: curso | AA14: nao | AB14: Oferta | AC14: 10 | AD14: 10 | AE14: 2 | AF14: 6 | AG14: Patricia Cavalcante | AH14: # Combo 10 Cursos de Danca do Ventre
A15: Portal Shakti Club — bellydance e tribal fusion | B15: =MIN(10, IF(N15="ativa",5,IF(N15="nova",4,IF(N15="esfriando",2,0)))+IF(L15>=9,3,IF(L15>=3,2,IF(L15>=1,1,0)))+IF(M15>=60,1.5,IF(M15>=30,1,IF(M15>=14,0.5,0)))+IF(V15>=50,1.5,IF(V15>=10,1,IF(V15>=1,0.5,0)))+IF(W15>=4,0.5,0)) -> 7.5 | C15: =ROUND(AC15*0.15+AD15*0.25+AE15*0.4+AF15*0.2,1) -> 5.3 | D15: =ROUND(B15*0.45+C15*0.55,1) -> 6.3 | E15: =IF(D15>=7,"Alta",IF(D15>=5,"Media","Baixa")) -> Media | F15: shaktistudioonline.com | G15: 1 | H15: danca-do-ventre | I15: 2 | J15: abrir pagina | K15: anuncio 3 criativo(s) | L15: 3 | M15: 81 | N15: nova | O15: descartar | P15: danca | Q15: danca-do-ventre | R15: 97 | S15: 210 | T15: 0.85 | U15: kiwify | V15: 0 | W15: 1 | X15: 2026-09-06 | Y15: 2026-09-06 | Z15: curso, comunidade | AA15: sim | AB15: Oferta | AC15: 10 | AD15: 7 | AE15: 2 | AF15: 6 | AG15: Luma Shakti Studio Online | AH15: # Portal Shakti Club
A16: Kit Mundinho de Papel | B16: =MIN(10, IF(N16="ativa",5,IF(N16="nova",4,IF(N16="esfriando",2,0)))+IF(L16>=9,3,IF(L16>=3,2,IF(L16>=1,1,0)))+IF(M16>=60,1.5,IF(M16>=30,1,IF(M16>=14,0.5,0)))+IF(V16>=50,1.5,IF(V16>=10,1,IF(V16>=1,0.5,0)))+IF(W16>=4,0.5,0)) -> 6 | C16: =ROUND(AC16*0.15+AD16*0.25+AE16*0.4+AF16*0.2,1) -> 6.1 | D16: =ROUND(B16*0.45+C16*0.55,1) -> 6.1 | E16: =IF(D16>=7,"Alta",IF(D16>=5,"Media","Baixa")) -> Media | F16: bibliotecainterativa.com | G16: 1 | H16: imprimivel-brincadeira | I16: 4 | J16: abrir pagina | K16: buscar na biblioteca | L16: 1 | M16: 54 | N16: nova | O16: observar | P16: comportamento-infantil | Q16: imprimivel-brincadeira | R16: 10 | S16: 10 | T16: 0.9 | U16: desconhecido | V16: 0 | W16: 1 | X16: 2026-08-31 | Y16: 2026-08-31 | Z16: ebook | AA16: nao | AB16: Oferta | AC16: 1 | AD16: 6 | AE16: 10 | AF16: 2 | AH16: # Kit Mundinho de Papel — R$ 10
A17: Tutu da Ju — assinatura de ballet classico online | B17: =MIN(10, IF(N17="ativa",5,IF(N17="nova",4,IF(N17="esfriando",2,0)))+IF(L17>=9,3,IF(L17>=3,2,IF(L17>=1,1,0)))+IF(M17>=60,1.5,IF(M17>=30,1,IF(M17>=14,0.5,0)))+IF(V17>=50,1.5,IF(V17>=10,1,IF(V17>=1,0.5,0)))+IF(W17>=4,0.5,0)) -> 6.5 | C17: =ROUND(AC17*0.15+AD17*0.25+AE17*0.4+AF17*0.2,1) -> 5.7 | D17: =ROUND(B17*0.45+C17*0.55,1) -> 6.1 | E17: =IF(D17>=7,"Alta",IF(D17>=5,"Media","Baixa")) -> Media | F17: conteudos.tutudaju.com | G17: 1 | H17: ballet-adulto | I17: 1 | J17: abrir pagina | K17: anuncio 1 criativo(s) | L17: 1 | M17: 137 | N17: nova | O17: observar | P17: danca | Q17: ballet-adulto | R17: 50 | S17: 150 | T17: 0.85 | U17: hotmart | V17: 0 | W17: 1 | X17: 2026-09-06 | Y17: 2026-09-06 | Z17: curso, comunidade | AA17: sim | AB17: Oferta | AC17: 9 | AD17: 7 | AE17: 3 | AF17: 7 | AG17: Tutu da Ju | AH17: # Tutu da Ju — assinatura
A18: Cursos Gratis Online | B18: =MIN(10, IF(N18="ativa",5,IF(N18="nova",4,IF(N18="esfriando",2,0)))+IF(L18>=9,3,IF(L18>=3,2,IF(L18>=1,1,0)))+IF(M18>=60,1.5,IF(M18>=30,1,IF(M18>=14,0.5,0)))+IF(V18>=50,1.5,IF(V18>=10,1,IF(V18>=1,0.5,0)))+IF(W18>=4,0.5,0)) -> 7 | C18: =ROUND(AC18*0.15+AD18*0.25+AE18*0.4+AF18*0.2,1) -> 5.4 | D18: =ROUND(B18*0.45+C18*0.55,1) -> 6.1 | E18: =IF(D18>=7,"Alta",IF(D18>=5,"Media","Baixa")) -> Media | F18: cursosgratisonline.com.br | G18: 1 | H18: taxa-para-liberar-certificado | I18: 4 | J18: abrir pagina | K18: buscar na biblioteca | L18: 0 | M18: 210 | N18: nova | O18: observar | P18: certificacao | Q18: taxa-para-liberar-certificado | R18: 79.9 | S18: 90 | T18: 0.9 | U18: desconhecido | V18: 114 | W18: 1 | X18: 2026-08-30 | Y18: 2026-08-30 | Z18: curso | AA18: nao | AB18: Oferta | AC18: 7 | AD18: 7 | AE18: 5 | AF18: 3 | AH18: # Cursos Gratis Online
A19: Google Captcha (TW Empreendimentos Digitais) | B19: =MIN(10, IF(N19="ativa",5,IF(N19="nova",4,IF(N19="esfriando",2,0)))+IF(L19>=9,3,IF(L19>=3,2,IF(L19>=1,1,0)))+IF(M19>=60,1.5,IF(M19>=30,1,IF(M19>=14,0.5,0)))+IF(V19>=50,1.5,IF(V19>=10,1,IF(V19>=1,0.5,0)))+IF(W19>=4,0.5,0)) -> 7.5 | C19: =ROUND(AC19*0.15+AD19*0.25+AE19*0.4+AF19*0.2,1) -> 4.8 | D19: =ROUND(B19*0.45+C19*0.55,1) -> 6 | E19: =IF(D19>=7,"Alta",IF(D19>=5,"Media","Baixa")) -> Media | F19: busca: Google Captcha ganhar dinheiro | G19: 1 | H19: taxa-para-liberar | I19: 3 | J19: — | K19: buscar na biblioteca | L19: 0 | M19: 61 | N19: ativa | O19: observar | P19: ganhar-dinheiro | Q19: taxa-para-liberar | R19: 50 | S19: 150 | T19: 0.95 | U19: perfectpay | V19: 39 | W19: 2 | X19: 2026-08-28 | Y19: 2026-08-29 | Z19: app | AA19: nao | AB19: Oferta | AC19: 9 | AD19: 8 | AE19: 2 | AF19: 3 | AH19: # Google Captcha (TW Empreendimentos Digitais)
A20: Alfabetinho — pacotes de atividades imprimiveis | B20: =MIN(10, IF(N20="ativa",5,IF(N20="nova",4,IF(N20="esfriando",2,0)))+IF(L20>=9,3,IF(L20>=3,2,IF(L20>=1,1,0)))+IF(M20>=60,1.5,IF(M20>=30,1,IF(M20>=14,0.5,0)))+IF(V20>=50,1.5,IF(V20>=10,1,IF(V20>=1,0.5,0)))+IF(W20>=4,0.5,0)) -> 6.5 | C20: =ROUND(AC20*0.15+AD20*0.25+AE20*0.4+AF20*0.2,1) -> 5.4 | D20: =ROUND(B20*0.45+C20*0.55,1) -> 5.9 | E20: =IF(D20>=7,"Alta",IF(D20>=5,"Media","Baixa")) -> Media | F20: alfabetinho.com.br | G20: 1 | H20: alfabetizacao-e-educacao-especial | I20: 1 | J20: abrir pagina | K20: buscar na biblioteca | L20: 0 | M20: 0 | N20: ativa | O20: observar | P20: material-pedagogico | Q20: alfabetizacao-e-educacao-especial | R20: 0 | S20: 0 | T20: 0.85 | U20: desconhecido | V20: 177 | W20: 1 | X20: 2026-08-29 | Y20: 2026-08-29 | Z20: ebook, curso | AA20: nao | AB20: Oferta | AC20: 0 | AD20: 7 | AE20: 7 | AF20: 4 | AH20: # Alfabetinho — pacotes de atividades imprimiveis
A21: Licao Kids — loja de atividades imprimiveis | B21: =MIN(10, IF(N21="ativa",5,IF(N21="nova",4,IF(N21="esfriando",2,0)))+IF(L21>=9,3,IF(L21>=3,2,IF(L21>=1,1,0)))+IF(M21>=60,1.5,IF(M21>=30,1,IF(M21>=14,0.5,0)))+IF(V21>=50,1.5,IF(V21>=10,1,IF(V21>=1,0.5,0)))+IF(W21>=4,0.5,0)) -> 6 | C21: =ROUND(AC21*0.15+AD21*0.25+AE21*0.4+AF21*0.2,1) -> 5.8 | D21: =ROUND(B21*0.45+C21*0.55,1) -> 5.9 | E21: =IF(D21>=7,"Alta",IF(D21>=5,"Media","Baixa")) -> Media | F21: licaokids.com.br | G21: 1 | H21: acervo-professora | I21: 2 | J21: abrir pagina | K21: buscar na biblioteca | L21: 1 | M21: 50 | N21: nova | O21: observar | P21: material-pedagogico | Q21: acervo-professora | R21: 9.9 | S21: 25 | T21: 0.9 | U21: desconhecido | V21: 0 | W21: 1 | X21: 2026-08-31 | Y21: 2026-08-31 | Z21: ebook | AA21: nao | AB21: Oferta | AC21: 3 | AD21: 6 | AE21: 7 | AF21: 5 | AH21: # Licao Kids — loja, nao funil
A22: Caderno Completo de Caligrafia — +300 atividades | B22: =MIN(10, IF(N22="ativa",5,IF(N22="nova",4,IF(N22="esfriando",2,0)))+IF(L22>=9,3,IF(L22>=3,2,IF(L22>=1,1,0)))+IF(M22>=60,1.5,IF(M22>=30,1,IF(M22>=14,0.5,0)))+IF(V22>=50,1.5,IF(V22>=10,1,IF(V22>=1,0.5,0)))+IF(W22>=4,0.5,0)) -> 6 | C22: =ROUND(AC22*0.15+AD22*0.25+AE22*0.4+AF22*0.2,1) -> 5.9 | D22: =ROUND(B22*0.45+C22*0.55,1) -> 5.9 | E22: =IF(D22>=7,"Alta",IF(D22>=5,"Media","Baixa")) -> Media | F22: mundocriativobr.shop | G22: 1 | H22: caligrafia | I22: 4 | J22: abrir pagina | K22: buscar na biblioteca | L22: 1 | M22: 47 | N22: nova | O22: observar | P22: material-pedagogico | Q22: caligrafia | R22: 10 | S22: 10 | T22: 0.9 | U22: desconhecido | V22: 0 | W22: 1 | X22: 2026-08-31 | Y22: 2026-08-31 | Z22: ebook | AA22: nao | AB22: Oferta | AC22: 1 | AD22: 6 | AE22: 9 | AF22: 3 | AH22: # Mundo Criativo — +300 atividades de caligrafia a R$ 10
A23: Atelie Digital Pequenas Estilistas — Colecao 2027 | B23: =MIN(10, IF(N23="ativa",5,IF(N23="nova",4,IF(N23="esfriando",2,0)))+IF(L23>=9,3,IF(L23>=3,2,IF(L23>=1,1,0)))+IF(M23>=60,1.5,IF(M23>=30,1,IF(M23>=14,0.5,0)))+IF(V23>=50,1.5,IF(V23>=10,1,IF(V23>=1,0.5,0)))+IF(W23>=4,0.5,0)) -> 5.5 | C23: =ROUND(AC23*0.15+AD23*0.25+AE23*0.4+AF23*0.2,1) -> 6.2 | D23: =ROUND(B23*0.45+C23*0.55,1) -> 5.9 | E23: =IF(D23>=7,"Alta",IF(D23>=5,"Media","Baixa")) -> Media | F23: pequenasestilistas.com | G23: 1 | H23: moda-infantil | I23: 1 | J23: abrir pagina | K23: buscar na biblioteca | L23: 2 | M23: 19 | N23: nova | O23: observar | P23: comportamento-infantil | Q23: moda-infantil | R23: 27.9 | S23: 27.9 | T23: 0.9 | U23: hotmart | V23: 0 | W23: 1 | X23: 2026-08-31 | Y23: 2026-08-31 | Z23: ebook | AA23: nao | AB23: Oferta | AC23: 3 | AD23: 3 | AE23: 9 | AF23: 7 | AH23: # Pequenas Estilistas — o mesmo PDF por 2,3x o preco do vizinho
A24: Escada de taxas decrescentes no pos-compra (nome nao capturado) | B24: =MIN(10, IF(N24="ativa",5,IF(N24="nova",4,IF(N24="esfriando",2,0)))+IF(L24>=9,3,IF(L24>=3,2,IF(L24>=1,1,0)))+IF(M24>=60,1.5,IF(M24>=30,1,IF(M24>=14,0.5,0)))+IF(V24>=50,1.5,IF(V24>=10,1,IF(V24>=1,0.5,0)))+IF(W24>=4,0.5,0)) -> 5.5 | C24: =ROUND(AC24*0.15+AD24*0.25+AE24*0.4+AF24*0.2,1) -> 6.1 | D24: =ROUND(B24*0.45+C24*0.55,1) -> 5.8 | E24: =IF(D24>=7,"Alta",IF(D24>=5,"Media","Baixa")) -> Media | F24: busca: curso taxa de liberação | G24: 1 | H24: taxa-para-liberar | I24: 3 | J24: — | K24: buscar na biblioteca | L24: 0 | M24: 0 | N24: ativa | O24: observar | P24: mecanica-de-checkout | Q24: taxa-para-liberar | R24: 27.9 | S24: 46.7 | T24: 0.9 | U24: perfectpay | V24: 1 | W24: 3 | X24: 2026-08-27 | Y24: 2026-08-29 | Z24: curso | AA24: nao | AB24: Oferta | AC24: 5 | AD24: 3 | AE24: 8 | AF24: 7 | AH24: # Escada de taxas decrescentes no pos-compra (nome nao capturado)
A25: Dicionario em Movimento — 90 movimentos para ministracao | B25: =MIN(10, IF(N25="ativa",5,IF(N25="nova",4,IF(N25="esfriando",2,0)))+IF(L25>=9,3,IF(L25>=3,2,IF(L25>=1,1,0)))+IF(M25>=60,1.5,IF(M25>=30,1,IF(M25>=14,0.5,0)))+IF(V25>=50,1.5,IF(V25>=10,1,IF(V25>=1,0.5,0)))+IF(W25>=4,0.5,0)) -> 6 | C25: =ROUND(AC25*0.15+AD25*0.25+AE25*0.4+AF25*0.2,1) -> 5.6 | D25: =ROUND(B25*0.45+C25*0.55,1) -> 5.8 | E25: =IF(D25>=7,"Alta",IF(D25>=5,"Media","Baixa")) -> Media | F25: dicionarioemmovimento.site | G25: 1 | H25: danca-gospel-ministerio | I25: 3 | J25: abrir pagina | K25: anuncio 3 criativo(s) | L25: 3 | M25: 12 | N25: nova | O25: observar | P25: danca | Q25: danca-gospel-ministerio | R25: 67 | S25: 67 | T25: 0.88 | U25: onprofit | V25: 0 | W25: 1 | X25: 2026-09-06 | Y25: 2026-09-06 | Z25: ebook, curso | AA25: nao | AB25: Oferta | AC25: 7 | AD25: 3 | AE25: 7 | AF25: 5 | AG25: Escola de Danca Louvor na Terra | AH25: # Dicionario em Movimento
A26: Aerobico Ritmado — aula pronta com certificado de 50h | B26: =MIN(10, IF(N26="ativa",5,IF(N26="nova",4,IF(N26="esfriando",2,0)))+IF(L26>=9,3,IF(L26>=3,2,IF(L26>=1,1,0)))+IF(M26>=60,1.5,IF(M26>=30,1,IF(M26>=14,0.5,0)))+IF(V26>=50,1.5,IF(V26>=10,1,IF(V26>=1,0.5,0)))+IF(W26>=4,0.5,0)) -> 6 | C26: =ROUND(AC26*0.15+AD26*0.25+AE26*0.4+AF26*0.2,1) -> 5.7 | D26: =ROUND(B26*0.45+C26*0.55,1) -> 5.8 | E26: =IF(D26>=7,"Alta",IF(D26>=5,"Media","Baixa")) -> Media | F26: galeraindica.com.br | G26: 1 | H26: danca-para-professor-de-edfisica | I26: 1 | J26: abrir pagina | K26: anuncio 3 criativo(s) | L26: 3 | M26: 10 | N26: nova | O26: observar | P26: danca | Q26: danca-para-professor-de-edfisica | R26: 67 | S26: 67 | T26: 0.88 | U26: hotmart | V26: 0 | W26: 1 | X26: 2026-09-06 | Y26: 2026-09-06 | Z26: curso, ebook | AA26: nao | AB26: Oferta | AC26: 7 | AD26: 4 | AE26: 7 | AF26: 4 | AG26: Galera da EdFisica | AH26: # Aerobico Ritmado — Galera da EdFisica
A27: The Soulmate Sketcher | B27: =MIN(10, IF(N27="ativa",5,IF(N27="nova",4,IF(N27="esfriando",2,0)))+IF(L27>=9,3,IF(L27>=3,2,IF(L27>=1,1,0)))+IF(M27>=60,1.5,IF(M27>=30,1,IF(M27>=14,0.5,0)))+IF(V27>=50,1.5,IF(V27>=10,1,IF(V27>=1,0.5,0)))+IF(W27>=4,0.5,0)) -> 5 | C27: =ROUND(AC27*0.15+AD27*0.25+AE27*0.4+AF27*0.2,1) -> 6.5 | D27: =ROUND(B27*0.45+C27*0.55,1) -> 5.8 | E27: =IF(D27>=7,"Alta",IF(D27>=5,"Media","Baixa")) -> Media | F27: thesoulmatesketcher.com | G27: 1 | H27: retrato-alma-gemea | I27: 3 | J27: abrir pagina | K27: buscar na biblioteca | L27: 0 | M27: 0 | N27: ativa | O27: observar | P27: esoterico | Q27: retrato-alma-gemea | R27: 27 | S27: 27 | T27: 0.97 | U27: proprio | V27: 0 | W27: 1 | X27: 2026-08-30 | Y27: 2026-08-30 | Z27: servico-digital | AA27: nao | AB27: Oferta | AC27: 7 | AD27: 4 | AE27: 8 | AF27: 6 | AH27: # The Soulmate Sketcher
A28: Portal do MEI Brasil | B28: =MIN(10, IF(N28="ativa",5,IF(N28="nova",4,IF(N28="esfriando",2,0)))+IF(L28>=9,3,IF(L28>=3,2,IF(L28>=1,1,0)))+IF(M28>=60,1.5,IF(M28>=30,1,IF(M28>=14,0.5,0)))+IF(V28>=50,1.5,IF(V28>=10,1,IF(V28>=1,0.5,0)))+IF(W28>=4,0.5,0)) -> 7 | C28: =ROUND(AC28*0.15+AD28*0.25+AE28*0.4+AF28*0.2,1) -> 4.7 | D28: =ROUND(B28*0.45+C28*0.55,1) -> 5.7 | E28: =IF(D28>=7,"Alta",IF(D28>=5,"Media","Baixa")) -> Media | F28: busca: abrir mei online | G28: 1 | H28: taxa-sobre-servico-publico-gratuito | I28: 2 | J28: — | K28: buscar na biblioteca | L28: 0 | M28: 210 | N28: nova | O28: observar | P28: servicos-empresariais | Q28: taxa-sobre-servico-publico-gratuito | R28: 0 | S28: 0 | T28: 0.95 | U28: desconhecido | V28: 889 | W28: 1 | X28: 2026-08-30 | Y28: 2026-08-30 | Z28: ebook | AA28: nao | AB28: Oferta | AC28: 0 | AD28: 10 | AE28: 4 | AF28: 3 | AH28: # Portal do MEI Brasil
A29: Certificado Curso Online — curso gratis, certificado R$ 139,90 | B29: =MIN(10, IF(N29="ativa",5,IF(N29="nova",4,IF(N29="esfriando",2,0)))+IF(L29>=9,3,IF(L29>=3,2,IF(L29>=1,1,0)))+IF(M29>=60,1.5,IF(M29>=30,1,IF(M29>=14,0.5,0)))+IF(V29>=50,1.5,IF(V29>=10,1,IF(V29>=1,0.5,0)))+IF(W29>=4,0.5,0)) -> 6.5 | C29: =ROUND(AC29*0.15+AD29*0.25+AE29*0.4+AF29*0.2,1) -> 5.2 | D29: =ROUND(B29*0.45+C29*0.55,1) -> 5.8 | E29: =IF(D29>=7,"Alta",IF(D29>=5,"Media","Baixa")) -> Media | F29: certificadocursosonline.com | G29: 1 | H29: taxa-para-liberar-certificado | I29: 4 | J29: abrir pagina | K29: buscar na biblioteca | L29: 0 | M29: 0 | N29: ativa | O29: observar | P29: certificacao | Q29: taxa-para-liberar-certificado | R29: 139.9 | S29: 139.9 | T29: 0.95 | U29: desconhecido | V29: 58 | W29: 1 | X29: 2026-08-29 | Y29: 2026-08-29 | Z29: curso | AA29: nao | AB29: Oferta | AC29: 9 | AD29: 4 | AE29: 5 | AF29: 4 | AH29: # Certificado Curso Online — curso gratis, certificado R$ 139,90
A30: Kit Do Rabisco a Letra Bonita — Uiara Oliveira | B30: =MIN(10, IF(N30="ativa",5,IF(N30="nova",4,IF(N30="esfriando",2,0)))+IF(L30>=9,3,IF(L30>=3,2,IF(L30>=1,1,0)))+IF(M30>=60,1.5,IF(M30>=30,1,IF(M30>=14,0.5,0)))+IF(V30>=50,1.5,IF(V30>=10,1,IF(V30>=1,0.5,0)))+IF(W30>=4,0.5,0)) -> 6 | C30: =ROUND(AC30*0.15+AD30*0.25+AE30*0.4+AF30*0.2,1) -> 5.2 | D30: =ROUND(B30*0.45+C30*0.55,1) -> 5.6 | E30: =IF(D30>=7,"Alta",IF(D30>=5,"Media","Baixa")) -> Media | F30: busca: do rabisco a letra bonita | G30: 1 | H30: caligrafia | I30: 4 | J30: — | K30: buscar na biblioteca | L30: 1 | M30: 32 | N30: nova | O30: observar | P30: material-pedagogico | Q30: caligrafia | R30: 0 | S30: 0 | T30: 0.9 | U30: desconhecido | V30: 0 | W30: 1 | X30: 2026-08-31 | Y30: 2026-08-31 | Z30: ebook | AA30: nao | AB30: Oferta | AC30: 0 | AD30: 4 | AE30: 9 | AF30: 3 | AH30: # Do Rabisco a Letra Bonita
A31: 250 Dinamicas de Ballet Prontas para Professoras | B31: =MIN(10, IF(N31="ativa",5,IF(N31="nova",4,IF(N31="esfriando",2,0)))+IF(L31>=9,3,IF(L31>=3,2,IF(L31>=1,1,0)))+IF(M31>=60,1.5,IF(M31>=30,1,IF(M31>=14,0.5,0)))+IF(V31>=50,1.5,IF(V31>=10,1,IF(V31>=1,0.5,0)))+IF(W31>=4,0.5,0)) -> 5 | C31: =ROUND(AC31*0.15+AD31*0.25+AE31*0.4+AF31*0.2,1) -> 5.9 | D31: =ROUND(B31*0.45+C31*0.55,1) -> 5.5 | E31: =IF(D31>=7,"Alta",IF(D31>=5,"Media","Baixa")) -> Media | F31: dinamicadeballet.netlify.app | G31: 1 | H31: material-para-professora-de-ballet | I31: 2 | J31: abrir pagina | K31: anuncio 2 criativo(s) | L31: 2 | M31: 9 | N31: nova | O31: observar | P31: danca | Q31: material-para-professora-de-ballet | R31: 10 | S31: 15 | T31: 0.93 | U31: payt | V31: 0 | W31: 1 | X31: 2026-09-06 | Y31: 2026-09-06 | Z31: ebook | AA31: nao | AB31: Oferta | AC31: 2 | AD31: 3 | AE31: 9 | AF31: 6 | AG31: Material da Prof | AH31: # 250 Dinamicas de Ballet — Material da Prof
A32: Angulo - Quiz de 60s que gera o retrato | B32: =MIN(10, IF(N32="ativa",5,IF(N32="nova",4,IF(N32="esfriando",2,0)))+IF(L32>=9,3,IF(L32>=3,2,IF(L32>=1,1,0)))+IF(M32>=60,1.5,IF(M32>=30,1,IF(M32>=14,0.5,0)))+IF(V32>=50,1.5,IF(V32>=10,1,IF(V32>=1,0.5,0)))+IF(W32>=4,0.5,0)) -> 4 | C32: =ROUND(AC32*0.15+AD32*0.25+AE32*0.4+AF32*0.2,1) -> 6.7 | D32: =ROUND(B32*0.45+C32*0.55,1) -> 5.5 | E32: =IF(D32>=7,"Alta",IF(D32>=5,"Media","Baixa")) -> Media | F32: par-sketch.app | G32: 1 | H32: retrato-alma-gemea | I32: 3 | J32: abrir pagina | K32: buscar na biblioteca | L32: 0 | M32: 0 | N32: nova | O32: observar | P32: esoterico | Q32: retrato-alma-gemea | R32: 0 | S32: 0 | T32: 0.97 | U32: desconhecido | V32: 0 | W32: 1 | X32: 2026-08-30 | Y32: 2026-08-30 | Z32: servico-digital | AA32: nao | AB32: Angulo | AC32: 0 | AD32: 9 | AE32: 9 | AF32: 4 | AH32: # Angulo — Quiz de 60s que gera o retrato
A33: Brumdance 3 em 1 — ballet, jazz e contemporaneo para ministrar | B33: =MIN(10, IF(N33="ativa",5,IF(N33="nova",4,IF(N33="esfriando",2,0)))+IF(L33>=9,3,IF(L33>=3,2,IF(L33>=1,1,0)))+IF(M33>=60,1.5,IF(M33>=30,1,IF(M33>=14,0.5,0)))+IF(V33>=50,1.5,IF(V33>=10,1,IF(V33>=1,0.5,0)))+IF(W33>=4,0.5,0)) -> 6 | C33: =ROUND(AC33*0.15+AD33*0.25+AE33*0.4+AF33*0.2,1) -> 4.7 | D33: =ROUND(B33*0.45+C33*0.55,1) -> 5.3 | E33: =IF(D33>=7,"Alta",IF(D33>=5,"Media","Baixa")) -> Media | F33: brumdance.com.br | G33: 1 | H33: danca-gospel-ministerio | I33: 3 | J33: abrir pagina | K33: anuncio 1 criativo(s) | L33: 1 | M33: 30 | N33: nova | O33: observar | P33: danca | Q33: danca-gospel-ministerio | R33: 40 | S33: 120 | T33: 0.85 | U33: hotmart | V33: 0 | W33: 1 | X33: 2026-09-06 | Y33: 2026-09-06 | Z33: curso | AA33: sim | AB33: Oferta | AC33: 8 | AD33: 5 | AE33: 3 | AF33: 5 | AG33: Brumdance | AH33: # Brumdance 3 em 1
A34: Arquivos STL para impressao 3D | B34: =MIN(10, IF(N34="ativa",5,IF(N34="nova",4,IF(N34="esfriando",2,0)))+IF(L34>=9,3,IF(L34>=3,2,IF(L34>=1,1,0)))+IF(M34>=60,1.5,IF(M34>=30,1,IF(M34>=14,0.5,0)))+IF(V34>=50,1.5,IF(V34>=10,1,IF(V34>=1,0.5,0)))+IF(W34>=4,0.5,0)) -> 3 | C34: =ROUND(AC34*0.15+AD34*0.25+AE34*0.4+AF34*0.2,1) -> 7.2 | D34: =ROUND(B34*0.45+C34*0.55,1) -> 5.3 | E34: =IF(D34>=7,"Alta",IF(D34>=5,"Media","Baixa")) -> Media | F34: busca: arquivos STL impressao 3D | G34: 1 | H34: impressao-3d | I34: 1 | J34: — | K34: buscar na biblioteca | L34: 0 | M34: 0 | N34: esfriando | O34: replicar | P34: artesanato-e-pdf | Q34: impressao-3d | R34: 30 | S34: 30 | T34: 0.85 | U34: wiapy | V34: 4 | W34: 5 | X34: 2026-08-16 | Y34: 2026-08-27 | Z34: ebook | AA34: nao | AB34: Angulo | AC34: 4 | AD34: 7 | AE34: 8 | AF34: 8 | AH34: # Arquivos STL para impressao 3D
A35: Angulo — bonecas e cenarios de papel imprimiveis | B35: =MIN(10, IF(N35="ativa",5,IF(N35="nova",4,IF(N35="esfriando",2,0)))+IF(L35>=9,3,IF(L35>=3,2,IF(L35>=1,1,0)))+IF(M35>=60,1.5,IF(M35>=30,1,IF(M35>=14,0.5,0)))+IF(V35>=50,1.5,IF(V35>=10,1,IF(V35>=1,0.5,0)))+IF(W35>=4,0.5,0)) -> 4 | C35: =ROUND(AC35*0.15+AD35*0.25+AE35*0.4+AF35*0.2,1) -> 6.4 | D35: =ROUND(B35*0.45+C35*0.55,1) -> 5.3 | E35: =IF(D35>=7,"Alta",IF(D35>=5,"Media","Baixa")) -> Media | F35: busca: bonecas de papel | G35: 1 | H35: imprimivel-brincadeira | I35: 4 | J35: — | K35: buscar na biblioteca | L35: 0 | M35: 0 | N35: nova | O35: observar | P35: comportamento-infantil | Q35: imprimivel-brincadeira | R35: 0 | S35: 0 | T35: 0.9 | U35: desconhecido | V35: 0 | W35: 1 | X35: 2026-08-31 | Y35: 2026-08-31 | Z35: ebook | AA35: nao | AB35: Angulo | AC35: 0 | AD35: 8 | AE35: 10 | AF35: 2 | AH35: # Angulo — bonecas e cenarios de papel imprimiveis
A36: Angulo — caligrafia e grafismo imprimivel | B36: =MIN(10, IF(N36="ativa",5,IF(N36="nova",4,IF(N36="esfriando",2,0)))+IF(L36>=9,3,IF(L36>=3,2,IF(L36>=1,1,0)))+IF(M36>=60,1.5,IF(M36>=30,1,IF(M36>=14,0.5,0)))+IF(V36>=50,1.5,IF(V36>=10,1,IF(V36>=1,0.5,0)))+IF(W36>=4,0.5,0)) -> 4 | C36: =ROUND(AC36*0.15+AD36*0.25+AE36*0.4+AF36*0.2,1) -> 6.5 | D36: =ROUND(B36*0.45+C36*0.55,1) -> 5.4 | E36: =IF(D36>=7,"Alta",IF(D36>=5,"Media","Baixa")) -> Media | F36: busca: caligrafia | G36: 1 | H36: caligrafia | I36: 4 | J36: — | K36: buscar na biblioteca | L36: 0 | M36: 0 | N36: nova | O36: observar | P36: material-pedagogico | Q36: caligrafia | R36: 0 | S36: 0 | T36: 0.9 | U36: desconhecido | V36: 0 | W36: 1 | X36: 2026-08-31 | Y36: 2026-08-31 | Z36: ebook | AA36: nao | AB36: Angulo | AC36: 0 | AD36: 9 | AE36: 9 | AF36: 3 | AH36: # Angulo — caligrafia e grafismo imprimivel
A37: Certifica Brasil — prova online, certificado pago | B37: =MIN(10, IF(N37="ativa",5,IF(N37="nova",4,IF(N37="esfriando",2,0)))+IF(L37>=9,3,IF(L37>=3,2,IF(L37>=1,1,0)))+IF(M37>=60,1.5,IF(M37>=30,1,IF(M37>=14,0.5,0)))+IF(V37>=50,1.5,IF(V37>=10,1,IF(V37>=1,0.5,0)))+IF(W37>=4,0.5,0)) -> 6 | C37: =ROUND(AC37*0.15+AD37*0.25+AE37*0.4+AF37*0.2,1) -> 4.8 | D37: =ROUND(B37*0.45+C37*0.55,1) -> 5.3 | E37: =IF(D37>=7,"Alta",IF(D37>=5,"Media","Baixa")) -> Media | F37: busca: certifica brasil | G37: 1 | H37: taxa-para-liberar-certificado | I37: 4 | J37: — | K37: buscar na biblioteca | L37: 0 | M37: 0 | N37: ativa | O37: observar | P37: certificacao | Q37: taxa-para-liberar-certificado | R37: 0 | S37: 0 | T37: 0.95 | U37: desconhecido | V37: 13 | W37: 2 | X37: 2026-08-29 | Y37: 2026-08-30 | Z37: ebook | AA37: nao | AB37: Oferta | AC37: 0 | AD37: 8 | AE37: 5 | AF37: 4 | AH37: # Certifica Brasil — prova online, certificado pago
A38: Movimentos de Adoracao — 40 coreografias gospel prontas | B38: =MIN(10, IF(N38="ativa",5,IF(N38="nova",4,IF(N38="esfriando",2,0)))+IF(L38>=9,3,IF(L38>=3,2,IF(L38>=1,1,0)))+IF(M38>=60,1.5,IF(M38>=30,1,IF(M38>=14,0.5,0)))+IF(V38>=50,1.5,IF(V38>=10,1,IF(V38>=1,0.5,0)))+IF(W38>=4,0.5,0)) -> 5 | C38: =ROUND(AC38*0.15+AD38*0.25+AE38*0.4+AF38*0.2,1) -> 5.6 | D38: =ROUND(B38*0.45+C38*0.55,1) -> 5.3 | E38: =IF(D38>=7,"Alta",IF(D38>=5,"Media","Baixa")) -> Media | F38: dancalouvor.com | G38: 1 | H38: danca-gospel-ministerio | I38: 3 | J38: abrir pagina | K38: anuncio 2 criativo(s) | L38: 2 | M38: 4 | N38: nova | O38: observar | P38: danca | Q38: danca-gospel-ministerio | R38: 19.9 | S38: 25 | T38: 0.92 | U38: kiwify | V38: 0 | W38: 1 | X38: 2026-09-06 | Y38: 2026-09-06 | Z38: ebook | AA38: nao | AB38: Oferta | AC38: 3 | AD38: 2 | AE38: 9 | AF38: 5 | AG38: Coreografias Gospel | AH38: # Movimentos de Adoracao — 40 coreografias gospel prontas
A39: Angulo — curso gratis, certificado pago | B39: =MIN(10, IF(N39="ativa",5,IF(N39="nova",4,IF(N39="esfriando",2,0)))+IF(L39>=9,3,IF(L39>=3,2,IF(L39>=1,1,0)))+IF(M39>=60,1.5,IF(M39>=30,1,IF(M39>=14,0.5,0)))+IF(V39>=50,1.5,IF(V39>=10,1,IF(V39>=1,0.5,0)))+IF(W39>=4,0.5,0)) -> 5 | C39: =ROUND(AC39*0.15+AD39*0.25+AE39*0.4+AF39*0.2,1) -> 5.5 | D39: =ROUND(B39*0.45+C39*0.55,1) -> 5.3 | E39: =IF(D39>=7,"Alta",IF(D39>=5,"Media","Baixa")) -> Media | F39: busca: curso gratuito com certificado | G39: 1 | H39: taxa-para-liberar-certificado | I39: 4 | J39: — | K39: buscar na biblioteca | L39: 0 | M39: 0 | N39: ativa | O39: observar | P39: certificacao | Q39: taxa-para-liberar-certificado | R39: 139.9 | S39: 139.9 | T39: 0.95 | U39: desconhecido | V39: 0 | W39: 2 | X39: 2026-08-29 | Y39: 2026-08-30 | Z39: curso, ebook | AA39: nao | AB39: Angulo | AC39: 9 | AD39: 6 | AE39: 5 | AF39: 3 | AH39: # Angulo — curso gratis, certificado pago
A40: Hinário em Movimento | B40: =MIN(10, IF(N40="ativa",5,IF(N40="nova",4,IF(N40="esfriando",2,0)))+IF(L40>=9,3,IF(L40>=3,2,IF(L40>=1,1,0)))+IF(M40>=60,1.5,IF(M40>=30,1,IF(M40>=14,0.5,0)))+IF(V40>=50,1.5,IF(V40>=10,1,IF(V40>=1,0.5,0)))+IF(W40>=4,0.5,0)) -> 2.5 | C40: =ROUND(AC40*0.15+AD40*0.25+AE40*0.4+AF40*0.2,1) -> 7.3 | D40: =ROUND(B40*0.45+C40*0.55,1) -> 5.1 | E40: =IF(D40>=7,"Alta",IF(D40>=5,"Media","Baixa")) -> Media | F40: busca: Hinário em Movimento | G40: 1 | H40: gospel-louvor | I40: 1 | J40: — | K40: buscar na biblioteca | L40: 0 | M40: 0 | N40: esfriando | O40: observar | P40: religioso | Q40: gospel-louvor | R40: 0 | S40: 27 | T40: 0.85 | U40: lastlink | V40: 2 | W40: 2 | X40: 2026-08-16 | Y40: 2026-08-22 | AA40: nao | AB40: Oferta | AC40: 4 | AD40: 6 | AE40: 9 | AF40: 8 | AH40: # Hinário em Movimento
A41: Angulo — cobrar pelo servico publico que e gratuito | B41: =MIN(10, IF(N41="ativa",5,IF(N41="nova",4,IF(N41="esfriando",2,0)))+IF(L41>=9,3,IF(L41>=3,2,IF(L41>=1,1,0)))+IF(M41>=60,1.5,IF(M41>=30,1,IF(M41>=14,0.5,0)))+IF(V41>=50,1.5,IF(V41>=10,1,IF(V41>=1,0.5,0)))+IF(W41>=4,0.5,0)) -> 5.5 | C41: =ROUND(AC41*0.15+AD41*0.25+AE41*0.4+AF41*0.2,1) -> 4.7 | D41: =ROUND(B41*0.45+C41*0.55,1) -> 5.1 | E41: =IF(D41>=7,"Alta",IF(D41>=5,"Media","Baixa")) -> Media | F41: busca: abrir mei segunda via certidao | G41: 1 | H41: taxa-sobre-servico-publico-gratuito | I41: 2 | J41: — | K41: buscar na biblioteca | L41: 0 | M41: 210 | N41: nova | O41: observar | P41: servicos-empresariais | Q41: taxa-sobre-servico-publico-gratuito | R41: 0 | S41: 0 | T41: 0.95 | U41: desconhecido | V41: 0 | W41: 1 | X41: 2026-08-30 | Y41: 2026-08-30 | Z41: ebook | AA41: nao | AB41: Angulo | AC41: 0 | AD41: 9 | AE41: 4 | AF41: 4 | AH41: # Angulo — cobrar pelo servico publico que e gratuito
A42: Music Creator Pro | B42: =MIN(10, IF(N42="ativa",5,IF(N42="nova",4,IF(N42="esfriando",2,0)))+IF(L42>=9,3,IF(L42>=3,2,IF(L42>=1,1,0)))+IF(M42>=60,1.5,IF(M42>=30,1,IF(M42>=14,0.5,0)))+IF(V42>=50,1.5,IF(V42>=10,1,IF(V42>=1,0.5,0)))+IF(W42>=4,0.5,0)) -> 3 | C42: =ROUND(AC42*0.15+AD42*0.25+AE42*0.4+AF42*0.2,1) -> 6.4 | D42: =ROUND(B42*0.45+C42*0.55,1) -> 4.9 | E42: =IF(D42>=7,"Alta",IF(D42>=5,"Media","Baixa")) -> Baixa | F42: busca: Music Creator Pro | G42: 1 | H42: pacote-arquivos | I42: 1 | J42: — | K42: buscar na biblioteca | L42: 0 | M42: 0 | N42: esfriando | O42: observar | P42: musica-producao | Q42: pacote-arquivos | R42: 0 | S42: 40 | T42: 0.95 | U42: wiapy | V42: 2 | W42: 4 | X42: 2026-08-22 | Y42: 2026-08-27 | Z42: pdf | AA42: nao | AB42: Oferta | AC42: 5 | AD42: 4 | AE42: 8 | AF42: 7 | AH42: # Music Creator Pro
A43: Treino Trinca (Pedro Lotz) | B43: =MIN(10, IF(N43="ativa",5,IF(N43="nova",4,IF(N43="esfriando",2,0)))+IF(L43>=9,3,IF(L43>=3,2,IF(L43>=1,1,0)))+IF(M43>=60,1.5,IF(M43>=30,1,IF(M43>=14,0.5,0)))+IF(V43>=50,1.5,IF(V43>=10,1,IF(V43>=1,0.5,0)))+IF(W43>=4,0.5,0)) -> 3 | C43: =ROUND(AC43*0.15+AD43*0.25+AE43*0.4+AF43*0.2,1) -> 6.5 | D43: =ROUND(B43*0.45+C43*0.55,1) -> 4.9 | E43: =IF(D43>=7,"Alta",IF(D43>=5,"Media","Baixa")) -> Baixa | F43: treinotrinca.com.br | G43: 1 | H43: treino-em-casa | I43: 1 | J43: abrir pagina | K43: buscar na biblioteca | L43: 0 | M43: 0 | N43: esfriando | O43: observar | P43: saude-estetica-fitness | Q43: treino-em-casa | R43: 37 | S43: 74 | T43: 0.85 | U43: hotmart | V43: 10 | W43: 3 | X43: 2026-08-16 | Y43: 2026-08-22 | Z43: curso, comunidade | AA43: sim | AB43: Oferta | AC43: 7 | AD43: 9 | AE43: 6 | AF43: 4 | AH43: # Treino Trinca (Pedro Lotz)
A44: Kit 1.000 Convites e Envelopes de Casamento (editáveis) | B44: =MIN(10, IF(N44="ativa",5,IF(N44="nova",4,IF(N44="esfriando",2,0)))+IF(L44>=9,3,IF(L44>=3,2,IF(L44>=1,1,0)))+IF(M44>=60,1.5,IF(M44>=30,1,IF(M44>=14,0.5,0)))+IF(V44>=50,1.5,IF(V44>=10,1,IF(V44>=1,0.5,0)))+IF(W44>=4,0.5,0)) -> 3 | C44: =ROUND(AC44*0.15+AD44*0.25+AE44*0.4+AF44*0.2,1) -> 6.3 | D44: =ROUND(B44*0.45+C44*0.55,1) -> 4.8 | E44: =IF(D44>=7,"Alta",IF(D44>=5,"Media","Baixa")) -> Baixa | F44: busca: convites de casamento editáveis | G44: 1 | H44: convites-casamento | I44: 1 | J44: — | K44: buscar na biblioteca | L44: 0 | M44: 0 | N44: esfriando | O44: observar | P44: artesanato-digital | Q44: convites-casamento | R44: 24.9 | S44: 25 | T44: 0.95 | U44: lowify | V44: 2 | W44: 5 | X44: 2026-08-21 | Y44: 2026-08-27 | Z44: planilha, pdf | AA44: nao | AB44: Oferta | AC44: 3 | AD44: 4 | AE44: 9 | AF44: 6 | AH44: # Kit 1.000 Convites e Envelopes de Casamento
A45: Unlovable | B45: =MIN(10, IF(N45="ativa",5,IF(N45="nova",4,IF(N45="esfriando",2,0)))+IF(L45>=9,3,IF(L45>=3,2,IF(L45>=1,1,0)))+IF(M45>=60,1.5,IF(M45>=30,1,IF(M45>=14,0.5,0)))+IF(V45>=50,1.5,IF(V45>=10,1,IF(V45>=1,0.5,0)))+IF(W45>=4,0.5,0)) -> 4 | C45: =ROUND(AC45*0.15+AD45*0.25+AE45*0.4+AF45*0.2,1) -> 5.6 | D45: =ROUND(B45*0.45+C45*0.55,1) -> 4.9 | E45: =IF(D45>=7,"Alta",IF(D45>=5,"Media","Baixa")) -> Baixa | F45: busca: unlovable | G45: 1 | H45: gerador-de-app | I45: 1 | J45: — | K45: buscar na biblioteca | L45: 0 | M45: 149 | N45: esfriando | O45: observar | P45: ia-ferramentas | Q45: gerador-de-app | R45: 57 | S45: 114 | T45: 0.8 | U45: kirvano | V45: 2 | W45: 3 | X45: 2026-08-21 | Y45: 2026-08-23 | Z45: app | AA45: sim | AB45: Oferta | AC45: 9 | AD45: 8 | AE45: 3 | AF45: 5 | AH45: # Unlovable
A46: Curso de Massagem Tantrica (Wiapy) | B46: =MIN(10, IF(N46="ativa",5,IF(N46="nova",4,IF(N46="esfriando",2,0)))+IF(L46>=9,3,IF(L46>=3,2,IF(L46>=1,1,0)))+IF(M46>=60,1.5,IF(M46>=30,1,IF(M46>=14,0.5,0)))+IF(V46>=50,1.5,IF(V46>=10,1,IF(V46>=1,0.5,0)))+IF(W46>=4,0.5,0)) -> 3 | C46: =ROUND(AC46*0.15+AD46*0.25+AE46*0.4+AF46*0.2,1) -> 6 | D46: =ROUND(B46*0.45+C46*0.55,1) -> 4.7 | E46: =IF(D46>=7,"Alta",IF(D46>=5,"Media","Baixa")) -> Baixa | F46: busca: massagem tântrica curso | G46: 1 | H46: massagem-tantrica | I46: 1 | J46: — | K46: buscar na biblioteca | L46: 0 | M46: 11 | N46: esfriando | O46: observar | P46: sexualidade-bemestar | Q46: massagem-tantrica | R46: 50 | S46: 50 | T46: 0.9 | U46: wiapy | V46: 2 | W46: 4 | X46: 2026-08-22 | Y46: 2026-08-27 | Z46: curso | AA46: nao | AB46: Oferta | AC46: 5 | AD46: 4 | AE46: 7 | AF46: 7 | AH46: # Curso de Massagem Tantrica
A47: Teacher ZAP — 7 idiomas pelo WhatsApp | B47: =MIN(10, IF(N47="ativa",5,IF(N47="nova",4,IF(N47="esfriando",2,0)))+IF(L47>=9,3,IF(L47>=3,2,IF(L47>=1,1,0)))+IF(M47>=60,1.5,IF(M47>=30,1,IF(M47>=14,0.5,0)))+IF(V47>=50,1.5,IF(V47>=10,1,IF(V47>=1,0.5,0)))+IF(W47>=4,0.5,0)) -> 2.5 | C47: =ROUND(AC47*0.15+AD47*0.25+AE47*0.4+AF47*0.2,1) -> 6.2 | D47: =ROUND(B47*0.45+C47*0.55,1) -> 4.5 | E47: =IF(D47>=7,"Alta",IF(D47>=5,"Media","Baixa")) -> Baixa | F47: busca: Teacher ZAP | G47: 1 | H47: ia-conversacional | I47: 1 | J47: — | K47: buscar na biblioteca | L47: 0 | M47: 0 | N47: esfriando | O47: observar | P47: idiomas | Q47: ia-conversacional | R47: 0 | S47: 47 | T47: 0.85 | U47: lastlink | V47: 2 | W47: 2 | X47: 2026-08-16 | Y47: 2026-08-22 | AA47: nao | AB47: Oferta | AC47: 5 | AD47: 8 | AE47: 6 | AF47: 5 | AH47: # Teacher ZAP — 7 idiomas pelo WhatsApp
A48: Forrozeiro do Zero (nome comercial nao confirmado) | B48: =MIN(10, IF(N48="ativa",5,IF(N48="nova",4,IF(N48="esfriando",2,0)))+IF(L48>=9,3,IF(L48>=3,2,IF(L48>=1,1,0)))+IF(M48>=60,1.5,IF(M48>=30,1,IF(M48>=14,0.5,0)))+IF(V48>=50,1.5,IF(V48>=10,1,IF(V48>=1,0.5,0)))+IF(W48>=4,0.5,0)) -> 5 | C48: =ROUND(AC48*0.15+AD48*0.25+AE48*0.4+AF48*0.2,1) -> 4.1 | D48: =ROUND(B48*0.45+C48*0.55,1) -> 4.5 | E48: =IF(D48>=7,"Alta",IF(D48>=5,"Media","Baixa")) -> Baixa | F48: quiz.forrozeirodozero.com.br | G48: 1 | H48: forro | I48: 2 | J48: abrir pagina | K48: anuncio 2 criativo(s) | L48: 2 | M48: 8 | N48: nova | O48: observar | P48: danca | Q48: forro | R48: 0 | S48: 0 | T48: 0.85 | U48: desconhecido | V48: 0 | W48: 1 | X48: 2026-09-06 | Y48: 2026-09-06 | Z48: curso | AA48: nao | AB48: Oferta | AC48: 0 | AD48: 2 | AE48: 6 | AF48: 6 | AG48: matheuscasbri | AH48: # Forrozeiro do Zero
A49: INSTALADOR ROBÔ PRONTO 2.0 | B49: =MIN(10, IF(N49="ativa",5,IF(N49="nova",4,IF(N49="esfriando",2,0)))+IF(L49>=9,3,IF(L49>=3,2,IF(L49>=1,1,0)))+IF(M49>=60,1.5,IF(M49>=30,1,IF(M49>=14,0.5,0)))+IF(V49>=50,1.5,IF(V49>=10,1,IF(V49>=1,0.5,0)))+IF(W49>=4,0.5,0)) -> 3 | C49: =ROUND(AC49*0.15+AD49*0.25+AE49*0.4+AF49*0.2,1) -> 5.6 | D49: =ROUND(B49*0.45+C49*0.55,1) -> 4.4 | E49: =IF(D49>=7,"Alta",IF(D49>=5,"Media","Baixa")) -> Baixa | F49: busca: INSTALADOR ROBÔ PRONTO 2.0 | G49: 1 | H49: automacao-robo | I49: 1 | J49: — | K49: buscar na biblioteca | L49: 0 | M49: 0 | N49: esfriando | O49: observar | P49: ganhar-dinheiro | Q49: automacao-robo | R49: 0 | S49: 97 | T49: 0.85 | U49: cakto | V49: 3 | W49: 5 | X49: 2026-08-16 | Y49: 2026-08-27 | AA49: nao | AB49: Oferta | AC49: 8 | AD49: 7 | AE49: 5 | AF49: 3 | AH49: # INSTALADOR ROBÔ PRONTO 2.0
A50: +350 Bonecas de Papel — Papel Mágico | B50: =MIN(10, IF(N50="ativa",5,IF(N50="nova",4,IF(N50="esfriando",2,0)))+IF(L50>=9,3,IF(L50>=3,2,IF(L50>=1,1,0)))+IF(M50>=60,1.5,IF(M50>=30,1,IF(M50>=14,0.5,0)))+IF(V50>=50,1.5,IF(V50>=10,1,IF(V50>=1,0.5,0)))+IF(W50>=4,0.5,0)) -> 2 | C50: =ROUND(AC50*0.15+AD50*0.25+AE50*0.4+AF50*0.2,1) -> 6.4 | D50: =ROUND(B50*0.45+C50*0.55,1) -> 4.4 | E50: =IF(D50>=7,"Alta",IF(D50>=5,"Media","Baixa")) -> Baixa | F50: papelmagicobr.netlify.app | G50: 1 | H50: tempo-de-tela | I50: 1 | J50: abrir pagina | K50: buscar na biblioteca | L50: 0 | M50: 0 | N50: esfriando | O50: observar | P50: imprimiveis-infantil | Q50: tempo-de-tela | R50: 12.9 | S50: 21 | T50: 0.95 | U50: lowify | V50: 0 | W50: 2 | X50: 2026-08-20 | Y50: 2026-08-31 | Z50: pdf | AA50: nao | AB50: Oferta | AC50: 3 | AD50: 6 | AE50: 10 | AF50: 2 | AH50: # +350 Bonecas de Papel — Papel Mágico
A51: Forro do Zero — Pe Descalco | B51: =MIN(10, IF(N51="ativa",5,IF(N51="nova",4,IF(N51="esfriando",2,0)))+IF(L51>=9,3,IF(L51>=3,2,IF(L51>=1,1,0)))+IF(M51>=60,1.5,IF(M51>=30,1,IF(M51>=14,0.5,0)))+IF(V51>=50,1.5,IF(V51>=10,1,IF(V51>=1,0.5,0)))+IF(W51>=4,0.5,0)) -> 4 | C51: =ROUND(AC51*0.15+AD51*0.25+AE51*0.4+AF51*0.2,1) -> 4.7 | D51: =ROUND(B51*0.45+C51*0.55,1) -> 4.4 | E51: =IF(D51>=7,"Alta",IF(D51>=5,"Media","Baixa")) -> Baixa | F51: pedescalcomkt.com.br | G51: 1 | H51: forro | I51: 2 | J51: abrir pagina | K51: buscar na biblioteca | L51: 0 | M51: 0 | N51: nova | O51: observar | P51: danca | Q51: forro | R51: 297 | S51: 297 | T51: 0.85 | U51: hotmart | V51: 0 | W51: 1 | X51: 2026-09-06 | Y51: 2026-09-06 | Z51: curso | AA51: nao | AB51: Oferta | AC51: 10 | AD51: 3 | AE51: 3 | AF51: 6 | AG51: Pe Descalco | AH51: # Forro do Zero — Pe Descalco
A52: Ângulo — Criança viciada em tela | B52: =MIN(10, IF(N52="ativa",5,IF(N52="nova",4,IF(N52="esfriando",2,0)))+IF(L52>=9,3,IF(L52>=3,2,IF(L52>=1,1,0)))+IF(M52>=60,1.5,IF(M52>=30,1,IF(M52>=14,0.5,0)))+IF(V52>=50,1.5,IF(V52>=10,1,IF(V52>=1,0.5,0)))+IF(W52>=4,0.5,0)) -> 0 | C52: =ROUND(AC52*0.15+AD52*0.25+AE52*0.4+AF52*0.2,1) -> 7.8 | D52: =ROUND(B52*0.45+C52*0.55,1) -> 4.3 | E52: =IF(D52>=7,"Alta",IF(D52>=5,"Media","Baixa")) -> Baixa | F52: busca: criança viciada celular | G52: 1 | H52: telas | I52: 2 | J52: — | K52: buscar na biblioteca | L52: 0 | M52: 0 | N52: morta | O52: replicar | P52: comportamento-infantil | Q52: telas | R52: 27 | S52: 50 | T52: 0.93 | U52: kiwify | V52: 0 | W52: 1 | X52: 2026-08-21 | Y52: 2026-08-21 | Z52: ebook, pdf | AA52: nao | AB52: Angulo | AC52: 6 | AD52: 6 | AE52: 9 | AF52: 9 | AH52: # Ângulo — Criança viciada em tela
A53: App de orcamento para eletricista + imprimiveis | B53: =MIN(10, IF(N53="ativa",5,IF(N53="nova",4,IF(N53="esfriando",2,0)))+IF(L53>=9,3,IF(L53>=3,2,IF(L53>=1,1,0)))+IF(M53>=60,1.5,IF(M53>=30,1,IF(M53>=14,0.5,0)))+IF(V53>=50,1.5,IF(V53>=10,1,IF(V53>=1,0.5,0)))+IF(W53>=4,0.5,0)) -> 0.5 | C53: =ROUND(AC53*0.15+AD53*0.25+AE53*0.4+AF53*0.2,1) -> 7.5 | D53: =ROUND(B53*0.45+C53*0.55,1) -> 4.4 | E53: =IF(D53>=7,"Alta",IF(D53>=5,"Media","Baixa")) -> Baixa | F53: busca: orcamento eletricista app | G53: 1 | H53: eletrica-residencial | I53: 1 | J53: — | K53: buscar na biblioteca | L53: 0 | M53: 0 | N53: morta | O53: replicar | P53: cursos-de-oficio | Q53: eletrica-residencial | R53: 27 | S53: 60 | T53: 0.85 | U53: wiapy | V53: 1 | W53: 1 | X53: 2026-08-16 | Y53: 2026-08-16 | Z53: planilha, ebook | AA53: nao | AB53: Angulo | AC53: 7 | AD53: 5 | AE53: 9 | AF53: 8 | AH53: # App de orcamento para eletricista + imprimiveis
A54: Artesanato, moldes e PDF criativo | B54: =MIN(10, IF(N54="ativa",5,IF(N54="nova",4,IF(N54="esfriando",2,0)))+IF(L54>=9,3,IF(L54>=3,2,IF(L54>=1,1,0)))+IF(M54>=60,1.5,IF(M54>=30,1,IF(M54>=14,0.5,0)))+IF(V54>=50,1.5,IF(V54>=10,1,IF(V54>=1,0.5,0)))+IF(W54>=4,0.5,0)) -> 0.5 | C54: =ROUND(AC54*0.15+AD54*0.25+AE54*0.4+AF54*0.2,1) -> 7.3 | D54: =ROUND(B54*0.45+C54*0.55,1) -> 4.2 | E54: =IF(D54>=7,"Alta",IF(D54>=5,"Media","Baixa")) -> Baixa | F54: busca: apostila de croche | G54: 1 | H54: moldes-e-croche | I54: 1 | J54: — | K54: buscar na biblioteca | L54: 0 | M54: 0 | N54: morta | O54: observar | P54: artesanato-e-pdf | Q54: moldes-e-croche | R54: 25 | S54: 25 | T54: 0.85 | U54: wiapy | V54: 6 | W54: 1 | X54: 2026-08-16 | Y54: 2026-08-16 | Z54: ebook | AA54: nao | AB54: Angulo | AC54: 3 | AD54: 8 | AE54: 10 | AF54: 4 | AH54: # Artesanato, moldes e PDF criativo
A55: Material pedagogico e apostilas imprimiveis | B55: =MIN(10, IF(N55="ativa",5,IF(N55="nova",4,IF(N55="esfriando",2,0)))+IF(L55>=9,3,IF(L55>=3,2,IF(L55>=1,1,0)))+IF(M55>=60,1.5,IF(M55>=30,1,IF(M55>=14,0.5,0)))+IF(V55>=50,1.5,IF(V55>=10,1,IF(V55>=1,0.5,0)))+IF(W55>=4,0.5,0)) -> 0.5 | C55: =ROUND(AC55*0.15+AD55*0.25+AE55*0.4+AF55*0.2,1) -> 7.2 | D55: =ROUND(B55*0.45+C55*0.55,1) -> 4.2 | E55: =IF(D55>=7,"Alta",IF(D55>=5,"Media","Baixa")) -> Baixa | F55: busca: atividades imprimiveis professor | G55: 1 | H55: alfabetizacao-e-planos-de-aula | I55: 1 | J55: — | K55: buscar na biblioteca | L55: 0 | M55: 0 | N55: morta | O55: observar | P55: material-pedagogico | Q55: alfabetizacao-e-planos-de-aula | R55: 27 | S55: 30 | T55: 0.85 | U55: wiapy | V55: 5 | W55: 1 | X55: 2026-08-16 | Y55: 2026-08-16 | Z55: ebook | AA55: nao | AB55: Angulo | AC55: 4 | AD55: 8 | AE55: 9 | AF55: 5 | AH55: # Material pedagogico e apostilas imprimiveis
A56: Ângulo — 'Será que meu filho tem...?' como isca de topo | B56: =MIN(10, IF(N56="ativa",5,IF(N56="nova",4,IF(N56="esfriando",2,0)))+IF(L56>=9,3,IF(L56>=3,2,IF(L56>=1,1,0)))+IF(M56>=60,1.5,IF(M56>=30,1,IF(M56>=14,0.5,0)))+IF(V56>=50,1.5,IF(V56>=10,1,IF(V56>=1,0.5,0)))+IF(W56>=4,0.5,0)) -> 0 | C56: =ROUND(AC56*0.15+AD56*0.25+AE56*0.4+AF56*0.2,1) -> 7.7 | D56: =ROUND(B56*0.45+C56*0.55,1) -> 4.2 | E56: =IF(D56>=7,"Alta",IF(D56>=5,"Media","Baixa")) -> Baixa | F56: busca: meu filho tem TDAH | G56: 1 | H56: tdah | I56: 2 | J56: — | K56: buscar na biblioteca | L56: 0 | M56: 0 | N56: morta | O56: replicar | P56: comportamento-infantil | Q56: tdah | R56: 19 | S56: 45 | T56: 0.93 | U56: hotmart | V56: 0 | W56: 1 | X56: 2026-08-21 | Y56: 2026-08-21 | Z56: ebook, pdf | AA56: nao | AB56: Angulo | AC56: 5 | AD56: 7 | AE56: 9 | AF56: 8 | AH56: # Ângulo — A dúvida diagnóstica como isca
A57: Renderizador de imagem com recarga na Google (nome nao capturado) | B57: =MIN(10, IF(N57="ativa",5,IF(N57="nova",4,IF(N57="esfriando",2,0)))+IF(L57>=9,3,IF(L57>=3,2,IF(L57>=1,1,0)))+IF(M57>=60,1.5,IF(M57>=30,1,IF(M57>=14,0.5,0)))+IF(V57>=50,1.5,IF(V57>=10,1,IF(V57>=1,0.5,0)))+IF(W57>=4,0.5,0)) -> 2.5 | C57: =ROUND(AC57*0.15+AD57*0.25+AE57*0.4+AF57*0.2,1) -> 5.6 | D57: =ROUND(B57*0.45+C57*0.55,1) -> 4.2 | E57: =IF(D57>=7,"Alta",IF(D57>=5,"Media","Baixa")) -> Baixa | F57: busca: renderizador de imagem IA | G57: 1 | H57: renderizador-wrapper-api | I57: 1 | J57: — | K57: buscar na biblioteca | L57: 0 | M57: 0 | N57: esfriando | O57: observar | P57: ferramentas-ia-design | Q57: renderizador-wrapper-api | R57: 0 | S57: 0 | T57: 0.95 | U57: kiwify | V57: 1 | W57: 1 | X57: 2026-08-24 | Y57: 2026-08-24 | Z57: app | AA57: nao | AB57: Oferta | AC57: 0 | AD57: 3 | AE57: 9 | AF57: 6 | AH57: # Renderizador de imagem com recarga na Google (nome nao capturado)
A58: Stalkeia.ai | B58: =MIN(10, IF(N58="ativa",5,IF(N58="nova",4,IF(N58="esfriando",2,0)))+IF(L58>=9,3,IF(L58>=3,2,IF(L58>=1,1,0)))+IF(M58>=60,1.5,IF(M58>=30,1,IF(M58>=14,0.5,0)))+IF(V58>=50,1.5,IF(V58>=10,1,IF(V58>=1,0.5,0)))+IF(W58>=4,0.5,0)) -> 3 | C58: =ROUND(AC58*0.15+AD58*0.25+AE58*0.4+AF58*0.2,1) -> 5.3 | D58: =ROUND(B58*0.45+C58*0.55,1) -> 4.3 | E58: =IF(D58>=7,"Alta",IF(D58>=5,"Media","Baixa")) -> Baixa | F58: stalkea.ai | G58: 1 | H58: espionar-redes-sociais | I58: 1 | J58: abrir pagina | K58: buscar na biblioteca | L58: 0 | M58: 0 | N58: esfriando | O58: observar | P58: espionagem-rastreamento | Q58: espionar-redes-sociais | R58: 37 | S58: 75 | T58: 0.85 | U58: perfectpay | V58: 7 | W58: 5 | X58: 2026-08-16 | Y58: 2026-08-24 | Z58: app | AA58: nao | AB58: Oferta | AC58: 7 | AD58: 8 | AE58: 4 | AF58: 3 | AH58: # Stalkeia.ai
A59: AUKS VIP / AUKS BOT | B59: =MIN(10, IF(N59="ativa",5,IF(N59="nova",4,IF(N59="esfriando",2,0)))+IF(L59>=9,3,IF(L59>=3,2,IF(L59>=1,1,0)))+IF(M59>=60,1.5,IF(M59>=30,1,IF(M59>=14,0.5,0)))+IF(V59>=50,1.5,IF(V59>=10,1,IF(V59>=1,0.5,0)))+IF(W59>=4,0.5,0)) -> 5.5 | C59: =ROUND(AC59*0.15+AD59*0.25+AE59*0.4+AF59*0.2,1) -> 3 | D59: =ROUND(B59*0.45+C59*0.55,1) -> 4.1 | E59: =IF(D59>=7,"Alta",IF(D59>=5,"Media","Baixa")) -> Baixa | F59: busca: AUKS bot | G59: 1 | H59: robo-de-operacao | I59: 1 | J59: — | K59: buscar na biblioteca | L59: 0 | M59: 0 | N59: ativa | O59: observar | P59: trading-automatizado | Q59: robo-de-operacao | R59: 0 | S59: 0 | T59: 0.85 | U59: perfectpay | V59: 1 | W59: 3 | X59: 2026-08-27 | Y59: 2026-08-29 | Z59: app | AA59: nao | AB59: Oferta | AC59: 0 | AD59: 3 | AE59: 4 | AF59: 3 | AH59: # AUKS VIP / AUKS BOT
A60: Cafe Premium — Barista Academy | B60: =MIN(10, IF(N60="ativa",5,IF(N60="nova",4,IF(N60="esfriando",2,0)))+IF(L60>=9,3,IF(L60>=3,2,IF(L60>=1,1,0)))+IF(M60>=60,1.5,IF(M60>=30,1,IF(M60>=14,0.5,0)))+IF(V60>=50,1.5,IF(V60>=10,1,IF(V60>=1,0.5,0)))+IF(W60>=4,0.5,0)) -> 2.5 | C60: =ROUND(AC60*0.15+AD60*0.25+AE60*0.4+AF60*0.2,1) -> 5.4 | D60: =ROUND(B60*0.45+C60*0.55,1) -> 4.1 | E60: =IF(D60>=7,"Alta",IF(D60>=5,"Media","Baixa")) -> Baixa | F60: busca: Cafe Premium Barista Academy | G60: 1 | H60: barista-cafeteria | I60: 1 | J60: — | K60: buscar na biblioteca | L60: 0 | M60: 0 | N60: esfriando | O60: observar | P60: gastronomia-profissional | Q60: barista-cafeteria | R60: 0 | S60: 0 | T60: 0.85 | U60: kirvano | V60: 1 | W60: 2 | X60: 2026-08-24 | Y60: 2026-08-27 | Z60: curso | AA60: nao | AB60: Oferta | AC60: 0 | AD60: 4 | AE60: 7 | AF60: 8 | AH60: # Cafe Premium — Barista Academy
A61: Foto com pet gerada por IA (Wiapy) | B61: =MIN(10, IF(N61="ativa",5,IF(N61="nova",4,IF(N61="esfriando",2,0)))+IF(L61>=9,3,IF(L61>=3,2,IF(L61>=1,1,0)))+IF(M61>=60,1.5,IF(M61>=30,1,IF(M61>=14,0.5,0)))+IF(V61>=50,1.5,IF(V61>=10,1,IF(V61>=1,0.5,0)))+IF(W61>=4,0.5,0)) -> 0.5 | C61: =ROUND(AC61*0.15+AD61*0.25+AE61*0.4+AF61*0.2,1) -> 7.1 | D61: =ROUND(B61*0.45+C61*0.55,1) -> 4.1 | E61: =IF(D61>=7,"Alta",IF(D61>=5,"Media","Baixa")) -> Baixa | F61: busca: Foto com pet gerada por IA | G61: 1 | H61: ia-imagem | I61: 1 | J61: — | K61: buscar na biblioteca | L61: 0 | M61: 0 | N61: morta | O61: observar | P61: pet | Q61: ia-imagem | R61: 0 | S61: 30 | T61: 0.85 | U61: wiapy | V61: 2 | W61: 2 | X61: 2026-08-16 | Y61: 2026-08-20 | AA61: nao | AB61: Oferta | AC61: 4 | AD61: 6 | AE61: 9 | AF61: 7 | AH61: # Foto com pet gerada por IA (Wiapy)
A62: Magias Amorosas - Hoodoo | B62: =MIN(10, IF(N62="ativa",5,IF(N62="nova",4,IF(N62="esfriando",2,0)))+IF(L62>=9,3,IF(L62>=3,2,IF(L62>=1,1,0)))+IF(M62>=60,1.5,IF(M62>=30,1,IF(M62>=14,0.5,0)))+IF(V62>=50,1.5,IF(V62>=10,1,IF(V62>=1,0.5,0)))+IF(W62>=4,0.5,0)) -> 2.5 | C62: =ROUND(AC62*0.15+AD62*0.25+AE62*0.4+AF62*0.2,1) -> 5.4 | D62: =ROUND(B62*0.45+C62*0.55,1) -> 4.1 | E62: =IF(D62>=7,"Alta",IF(D62>=5,"Media","Baixa")) -> Baixa | F62: busca: magia amorosa hoodoo curso | G62: 1 | H62: magia-amorosa | I62: 1 | J62: — | K62: buscar na biblioteca | L62: 0 | M62: 0 | N62: esfriando | O62: observar | P62: esoterico | Q62: magia-amorosa | R62: 0 | S62: 0 | T62: 0.95 | U62: kiwify | V62: 1 | W62: 2 | X62: 2026-08-23 | Y62: 2026-08-24 | Z62: curso | AA62: nao | AB62: Oferta | AC62: 0 | AD62: 3 | AE62: 8 | AF62: 7 | AH62: # Magias Amorosas - Hoodoo
A63: Parábolas Kids — 1.001 parábolas bíblicas para crianças | B63: =MIN(10, IF(N63="ativa",5,IF(N63="nova",4,IF(N63="esfriando",2,0)))+IF(L63>=9,3,IF(L63>=3,2,IF(L63>=1,1,0)))+IF(M63>=60,1.5,IF(M63>=30,1,IF(M63>=14,0.5,0)))+IF(V63>=50,1.5,IF(V63>=10,1,IF(V63>=1,0.5,0)))+IF(W63>=4,0.5,0)) -> 0.5 | C63: =ROUND(AC63*0.15+AD63*0.25+AE63*0.4+AF63*0.2,1) -> 7.2 | D63: =ROUND(B63*0.45+C63*0.55,1) -> 4.2 | E63: =IF(D63>=7,"Alta",IF(D63>=5,"Media","Baixa")) -> Baixa | F63: parabolaskids.com.br | G63: 1 | H63: valores-religiao | I63: 1 | J63: abrir pagina | K63: buscar na biblioteca | L63: 0 | M63: 0 | N63: morta | O63: replicar | P63: comportamento-infantil | Q63: valores-religiao | R63: 37 | S63: 37 | T63: 0.95 | U63: kiwify | V63: 1 | W63: 1 | X63: 2026-08-21 | Y63: 2026-08-21 | Z63: pdf | AA63: nao | AB63: Oferta | AC63: 4 | AD63: 7 | AE63: 9 | AF63: 6 | AH63: # Parábolas Kids
A64: Novelas turcas, doramas e mini dramas | B64: =MIN(10, IF(N64="ativa",5,IF(N64="nova",4,IF(N64="esfriando",2,0)))+IF(L64>=9,3,IF(L64>=3,2,IF(L64>=1,1,0)))+IF(M64>=60,1.5,IF(M64>=30,1,IF(M64>=14,0.5,0)))+IF(V64>=50,1.5,IF(V64>=10,1,IF(V64>=1,0.5,0)))+IF(W64>=4,0.5,0)) -> 3 | C64: =ROUND(AC64*0.15+AD64*0.25+AE64*0.4+AF64*0.2,1) -> 4.9 | D64: =ROUND(B64*0.45+C64*0.55,1) -> 4 | E64: =IF(D64>=7,"Alta",IF(D64>=5,"Media","Baixa")) -> Baixa | F64: busca: novelas turcas dubladas | G64: 1 | H64: catalogo-novelas | I64: 1 | J64: — | K64: buscar na biblioteca | L64: 0 | M64: 0 | N64: esfriando | O64: descartar | P64: streaming-e-acesso | Q64: catalogo-novelas | R64: 10 | S64: 20 | T64: 0.85 | U64: lowify | V64: 9 | W64: 5 | X64: 2026-08-16 | Y64: 2026-08-27 | Z64: app | AA64: sim | AB64: Angulo | AC64: 3 | AD64: 8 | AE64: 3 | AF64: 6 | AH64: # Novelas turcas, doramas e mini dramas
A65: Aula Desplugada — +500 atividades BNCC sem computador | B65: =MIN(10, IF(N65="ativa",5,IF(N65="nova",4,IF(N65="esfriando",2,0)))+IF(L65>=9,3,IF(L65>=3,2,IF(L65>=1,1,0)))+IF(M65>=60,1.5,IF(M65>=30,1,IF(M65>=14,0.5,0)))+IF(V65>=50,1.5,IF(V65>=10,1,IF(V65>=1,0.5,0)))+IF(W65>=4,0.5,0)) -> 0 | C65: =ROUND(AC65*0.15+AD65*0.25+AE65*0.4+AF65*0.2,1) -> 7 | D65: =ROUND(B65*0.45+C65*0.55,1) -> 3.9 | E65: =IF(D65>=7,"Alta",IF(D65>=5,"Media","Baixa")) -> Baixa | F65: auladesplugada.netlify.app | G65: 1 | H65: bncc-atividades | I65: 1 | J65: abrir pagina | K65: buscar na biblioteca | L65: 0 | M65: 0 | N65: morta | O65: replicar | P65: educacao | Q65: bncc-atividades | R65: 10 | S65: 38 | T65: 0.92 | U65: ggcheckout | V65: 0 | W65: 1 | X65: 2026-08-16 | Y65: 2026-08-16 | Z65: pdf | AA65: nao | AB65: Oferta | AC65: 4 | AD65: 7 | AE65: 8 | AF65: 7 | AH65: # Aula Desplugada
A66: Carrosseis Magneticos | B66: =MIN(10, IF(N66="ativa",5,IF(N66="nova",4,IF(N66="esfriando",2,0)))+IF(L66>=9,3,IF(L66>=3,2,IF(L66>=1,1,0)))+IF(M66>=60,1.5,IF(M66>=30,1,IF(M66>=14,0.5,0)))+IF(V66>=50,1.5,IF(V66>=10,1,IF(V66>=1,0.5,0)))+IF(W66>=4,0.5,0)) -> 2.5 | C66: =ROUND(AC66*0.15+AD66*0.25+AE66*0.4+AF66*0.2,1) -> 5.2 | D66: =ROUND(B66*0.45+C66*0.55,1) -> 4 | E66: =IF(D66>=7,"Alta",IF(D66>=5,"Media","Baixa")) -> Baixa | F66: busca: Carrosséis Magnéticos | G66: 1 | H66: templates-instagram | I66: 1 | J66: — | K66: buscar na biblioteca | L66: 0 | M66: 0 | N66: esfriando | O66: observar | P66: marketing-conteudo | Q66: templates-instagram | R66: 0 | S66: 0 | T66: 0.9 | U66: kiwify | V66: 1 | W66: 2 | X66: 2026-08-27 | Y66: 2026-08-28 | Z66: planilha | AA66: nao | AB66: Oferta | AC66: 0 | AD66: 3 | AE66: 9 | AF66: 4 | AH66: # Carrosseis Magneticos
A67: Robô Hacker Book — Gerador de E-books no Automático | B67: =MIN(10, IF(N67="ativa",5,IF(N67="nova",4,IF(N67="esfriando",2,0)))+IF(L67>=9,3,IF(L67>=3,2,IF(L67>=1,1,0)))+IF(M67>=60,1.5,IF(M67>=30,1,IF(M67>=14,0.5,0)))+IF(V67>=50,1.5,IF(V67>=10,1,IF(V67>=1,0.5,0)))+IF(W67>=4,0.5,0)) -> 0.5 | C67: =ROUND(AC67*0.15+AD67*0.25+AE67*0.4+AF67*0.2,1) -> 6.6 | D67: =ROUND(B67*0.45+C67*0.55,1) -> 3.9 | E67: =IF(D67>=7,"Alta",IF(D67>=5,"Media","Baixa")) -> Baixa | F67: busca: Robô Hacker Book | G67: 1 | H67: ferramentas-ia | I67: 1 | J67: — | K67: buscar na biblioteca | L67: 0 | M67: 0 | N67: morta | O67: observar | P67: marketing-digital | Q67: ferramentas-ia | R67: 0 | S67: 60 | T67: 0.85 | U67: kirvano | V67: 4 | W67: 1 | X67: 2026-08-16 | Y67: 2026-08-16 | AA67: nao | AB67: Oferta | AC67: 7 | AD67: 7 | AE67: 8 | AF67: 3 | AH67: # Robô Hacker Book — Gerador de E-books no Automático
A68: Ângulo — Kit imprimível para criança com TEA | B68: =MIN(10, IF(N68="ativa",5,IF(N68="nova",4,IF(N68="esfriando",2,0)))+IF(L68>=9,3,IF(L68>=3,2,IF(L68>=1,1,0)))+IF(M68>=60,1.5,IF(M68>=30,1,IF(M68>=14,0.5,0)))+IF(V68>=50,1.5,IF(V68>=10,1,IF(V68>=1,0.5,0)))+IF(W68>=4,0.5,0)) -> 0 | C68: =ROUND(AC68*0.15+AD68*0.25+AE68*0.4+AF68*0.2,1) -> 7.2 | D68: =ROUND(B68*0.45+C68*0.55,1) -> 4 | E68: =IF(D68>=7,"Alta",IF(D68>=5,"Media","Baixa")) -> Baixa | F68: busca: autismo atividades criança | G68: 1 | H68: tea-autismo | I68: 3 | J68: — | K68: buscar na biblioteca | L68: 0 | M68: 0 | N68: morta | O68: replicar | P68: comportamento-infantil | Q68: tea-autismo | R68: 37 | S68: 40 | T68: 0.95 | U68: hotmart | V68: 0 | W68: 1 | X68: 2026-08-21 | Y68: 2026-08-21 | Z68: pdf | AA68: nao | AB68: Angulo | AC68: 4 | AD68: 7 | AE68: 9 | AF68: 6 | AH68: # Ângulo — Kit imprimível TEA
A69: Fabrica de Low Ticket | B69: =MIN(10, IF(N69="ativa",5,IF(N69="nova",4,IF(N69="esfriando",2,0)))+IF(L69>=9,3,IF(L69>=3,2,IF(L69>=1,1,0)))+IF(M69>=60,1.5,IF(M69>=30,1,IF(M69>=14,0.5,0)))+IF(V69>=50,1.5,IF(V69>=10,1,IF(V69>=1,0.5,0)))+IF(W69>=4,0.5,0)) -> 3 | C69: =ROUND(AC69*0.15+AD69*0.25+AE69*0.4+AF69*0.2,1) -> 4.7 | D69: =ROUND(B69*0.45+C69*0.55,1) -> 3.9 | E69: =IF(D69>=7,"Alta",IF(D69>=5,"Media","Baixa")) -> Baixa | F69: busca: fábrica de low ticket | G69: 1 | H69: metodo-low-ticket | I69: 1 | J69: — | K69: buscar na biblioteca | L69: 0 | M69: 0 | N69: esfriando | O69: observar | P69: ganhar-dinheiro | Q69: metodo-low-ticket | R69: 0 | S69: 97 | T69: 0.9 | U69: ticto | V69: 2 | W69: 4 | X69: 2026-08-22 | Y69: 2026-08-27 | Z69: curso | AA69: nao | AB69: Oferta | AC69: 7 | AD69: 4 | AE69: 5 | AF69: 3 | AH69: # Fabrica de Low Ticket
A70: Lowzap (+ upsell Low Scale) | B70: =MIN(10, IF(N70="ativa",5,IF(N70="nova",4,IF(N70="esfriando",2,0)))+IF(L70>=9,3,IF(L70>=3,2,IF(L70>=1,1,0)))+IF(M70>=60,1.5,IF(M70>=30,1,IF(M70>=14,0.5,0)))+IF(V70>=50,1.5,IF(V70>=10,1,IF(V70>=1,0.5,0)))+IF(W70>=4,0.5,0)) -> 2.5 | C70: =ROUND(AC70*0.15+AD70*0.25+AE70*0.4+AF70*0.2,1) -> 5.2 | D70: =ROUND(B70*0.45+C70*0.55,1) -> 4 | E70: =IF(D70>=7,"Alta",IF(D70>=5,"Media","Baixa")) -> Baixa | F70: busca: lowzap | G70: 1 | H70: whatsapp-ferramentas | I70: 2 | J70: — | K70: buscar na biblioteca | L70: 0 | M70: 0 | N70: esfriando | O70: observar | P70: ganhar-dinheiro | Q70: whatsapp-ferramentas | R70: 0 | S70: 97 | T70: 0.85 | U70: kirvano | V70: 2 | W70: 3 | X70: 2026-08-21 | Y70: 2026-08-23 | Z70: curso, app | AA70: nao | AB70: Oferta | AC70: 7 | AD70: 6 | AE70: 5 | AF70: 3 | AH70: # Lowzap (+ upsell Low Scale)
A71: Desafio 21 Dias com Deus (clone .shop) | B71: =MIN(10, IF(N71="ativa",5,IF(N71="nova",4,IF(N71="esfriando",2,0)))+IF(L71>=9,3,IF(L71>=3,2,IF(L71>=1,1,0)))+IF(M71>=60,1.5,IF(M71>=30,1,IF(M71>=14,0.5,0)))+IF(V71>=50,1.5,IF(V71>=10,1,IF(V71>=1,0.5,0)))+IF(W71>=4,0.5,0)) -> 0 | C71: =ROUND(AC71*0.15+AD71*0.25+AE71*0.4+AF71*0.2,1) -> 7 | D71: =ROUND(B71*0.45+C71*0.55,1) -> 3.9 | E71: =IF(D71>=7,"Alta",IF(D71>=5,"Media","Baixa")) -> Baixa | F71: imperdivel.ofertaslimitadasmaterial.shop | G71: 1 | H71: devocional-diario | I71: 3 | J71: abrir pagina | K71: buscar na biblioteca | L71: 0 | M71: 0 | N71: morta | O71: descartar | P71: religioso | Q71: devocional-diario | R71: 27 | S71: 27 | T71: 0.85 | U71: desconhecido | V71: 0 | W71: 1 | X71: 2026-08-21 | Y71: 2026-08-21 | Z71: ebook | AA71: nao | AB71: Oferta | AC71: 4 | AD71: 8 | AE71: 10 | AF71: 2 | AH71: # Desafio 21 Dias com Deus (clone .shop)
A72: App de histórias — entrega via Telegram (Lowify) | B72: =MIN(10, IF(N72="ativa",5,IF(N72="nova",4,IF(N72="esfriando",2,0)))+IF(L72>=9,3,IF(L72>=3,2,IF(L72>=1,1,0)))+IF(M72>=60,1.5,IF(M72>=30,1,IF(M72>=14,0.5,0)))+IF(V72>=50,1.5,IF(V72>=10,1,IF(V72>=1,0.5,0)))+IF(W72>=4,0.5,0)) -> 0.5 | C72: =ROUND(AC72*0.15+AD72*0.25+AE72*0.4+AF72*0.2,1) -> 6.5 | D72: =ROUND(B72*0.45+C72*0.55,1) -> 3.8 | E72: =IF(D72>=7,"Alta",IF(D72>=5,"Media","Baixa")) -> Baixa | F72: busca: App de histórias | G72: 1 | H72: leitura-ficcao | I72: 1 | J72: — | K72: buscar na biblioteca | L72: 0 | M72: 0 | N72: morta | O72: observar | P72: entretenimento | Q72: leitura-ficcao | R72: 0 | S72: 19 | T72: 0.85 | U72: lowify | V72: 3 | W72: 1 | X72: 2026-08-16 | Y72: 2026-08-16 | AA72: nao | AB72: Oferta | AC72: 2 | AD72: 8 | AE72: 9 | AF72: 3 | AH72: # App de histórias — entrega via Telegram (Lowify)
A73: Ângulo — Bebê dormir a noite toda | B73: =MIN(10, IF(N73="ativa",5,IF(N73="nova",4,IF(N73="esfriando",2,0)))+IF(L73>=9,3,IF(L73>=3,2,IF(L73>=1,1,0)))+IF(M73>=60,1.5,IF(M73>=30,1,IF(M73>=14,0.5,0)))+IF(V73>=50,1.5,IF(V73>=10,1,IF(V73>=1,0.5,0)))+IF(W73>=4,0.5,0)) -> 0 | C73: =ROUND(AC73*0.15+AD73*0.25+AE73*0.4+AF73*0.2,1) -> 6.9 | D73: =ROUND(B73*0.45+C73*0.55,1) -> 3.8 | E73: =IF(D73>=7,"Alta",IF(D73>=5,"Media","Baixa")) -> Baixa | F73: busca: bebê dormir noite toda | G73: 1 | H73: sono-infantil | I73: 1 | J73: — | K73: buscar na biblioteca | L73: 0 | M73: 0 | N73: morta | O73: observar | P73: comportamento-infantil | Q73: sono-infantil | R73: 27 | S73: 60 | T73: 0.92 | U73: hotmart | V73: 0 | W73: 1 | X73: 2026-08-21 | Y73: 2026-08-21 | Z73: ebook, curso | AA73: nao | AB73: Angulo | AC73: 7 | AD73: 8 | AE73: 8 | AF73: 3 | AH73: # Ângulo — Sono infantil
A74: Ângulo — Birra, teimosia e filho que não obedece | B74: =MIN(10, IF(N74="ativa",5,IF(N74="nova",4,IF(N74="esfriando",2,0)))+IF(L74>=9,3,IF(L74>=3,2,IF(L74>=1,1,0)))+IF(M74>=60,1.5,IF(M74>=30,1,IF(M74>=14,0.5,0)))+IF(V74>=50,1.5,IF(V74>=10,1,IF(V74>=1,0.5,0)))+IF(W74>=4,0.5,0)) -> 0 | C74: =ROUND(AC74*0.15+AD74*0.25+AE74*0.4+AF74*0.2,1) -> 6.9 | D74: =ROUND(B74*0.45+C74*0.55,1) -> 3.8 | E74: =IF(D74>=7,"Alta",IF(D74>=5,"Media","Baixa")) -> Baixa | F74: busca: birra criança | G74: 1 | H74: birra-disciplina | I74: 5 | J74: — | K74: buscar na biblioteca | L74: 0 | M74: 0 | N74: morta | O74: observar | P74: comportamento-infantil | Q74: birra-disciplina | R74: 34.9 | S74: 40 | T74: 0.92 | U74: hotmart | V74: 0 | W74: 1 | X74: 2026-08-21 | Y74: 2026-08-21 | Z74: ebook | AA74: nao | AB74: Angulo | AC74: 5 | AD74: 7 | AE74: 9 | AF74: 4 | AH74: # Ângulo — Birra e teimosia
A75: Desafio Romanos 12:2 | B75: =MIN(10, IF(N75="ativa",5,IF(N75="nova",4,IF(N75="esfriando",2,0)))+IF(L75>=9,3,IF(L75>=3,2,IF(L75>=1,1,0)))+IF(M75>=60,1.5,IF(M75>=30,1,IF(M75>=14,0.5,0)))+IF(V75>=50,1.5,IF(V75>=10,1,IF(V75>=1,0.5,0)))+IF(W75>=4,0.5,0)) -> 0 | C75: =ROUND(AC75*0.15+AD75*0.25+AE75*0.4+AF75*0.2,1) -> 6.9 | D75: =ROUND(B75*0.45+C75*0.55,1) -> 3.8 | E75: =IF(D75>=7,"Alta",IF(D75>=5,"Media","Baixa")) -> Baixa | F75: desafioromanos.stefannymartinez.com.br | G75: 1 | H75: mulher-crista-saude-mental | I75: 2 | J75: abrir pagina | K75: buscar na biblioteca | L75: 0 | M75: 0 | N75: morta | O75: observar | P75: religioso | Q75: mulher-crista-saude-mental | R75: 147 | S75: 147 | T75: 0.85 | U75: hotmart | V75: 0 | W75: 1 | X75: 2026-08-21 | Y75: 2026-08-21 | Z75: curso, ebook, fisico | AA75: nao | AB75: Oferta | AC75: 8 | AD75: 6 | AE75: 7 | AF75: 7 | AH75: # Desafio Romanos 12:2
A76: Kit 300 Aulas Prontas de Educação Física — Sem Improviso | B76: =MIN(10, IF(N76="ativa",5,IF(N76="nova",4,IF(N76="esfriando",2,0)))+IF(L76>=9,3,IF(L76>=3,2,IF(L76>=1,1,0)))+IF(M76>=60,1.5,IF(M76>=30,1,IF(M76>=14,0.5,0)))+IF(V76>=50,1.5,IF(V76>=10,1,IF(V76>=1,0.5,0)))+IF(W76>=4,0.5,0)) -> 0 | C76: =ROUND(AC76*0.15+AD76*0.25+AE76*0.4+AF76*0.2,1) -> 7 | D76: =ROUND(B76*0.45+C76*0.55,1) -> 3.9 | E76: =IF(D76>=7,"Alta",IF(D76>=5,"Media","Baixa")) -> Baixa | F76: kit-300aulas-edfisica.netlify.app | G76: 1 | H76: educacao-fisica-escolar | I76: 1 | J76: abrir pagina | K76: buscar na biblioteca | L76: 0 | M76: 0 | N76: morta | O76: replicar | P76: educacao | Q76: educacao-fisica-escolar | R76: 27.9 | S76: 40 | T76: 0.92 | U76: wiapy | V76: 0 | W76: 2 | X76: 2026-08-16 | Y76: 2026-08-20 | Z76: pdf, area-membros | AA76: nao | AB76: Oferta | AC76: 4 | AD76: 7 | AE76: 9 | AF76: 5 | AH76: # Kit 300 Aulas Prontas de Educação Física
A77: Desafio 21 Dias com Deus (Traco Home) | B77: =MIN(10, IF(N77="ativa",5,IF(N77="nova",4,IF(N77="esfriando",2,0)))+IF(L77>=9,3,IF(L77>=3,2,IF(L77>=1,1,0)))+IF(M77>=60,1.5,IF(M77>=30,1,IF(M77>=14,0.5,0)))+IF(V77>=50,1.5,IF(V77>=10,1,IF(V77>=1,0.5,0)))+IF(W77>=4,0.5,0)) -> 0 | C77: =ROUND(AC77*0.15+AD77*0.25+AE77*0.4+AF77*0.2,1) -> 7 | D77: =ROUND(B77*0.45+C77*0.55,1) -> 3.9 | E77: =IF(D77>=7,"Alta",IF(D77>=5,"Media","Baixa")) -> Baixa | F77: tracohome.com.br | G77: 1 | H77: devocional-diario | I77: 3 | J77: abrir pagina | K77: buscar na biblioteca | L77: 0 | M77: 0 | N77: morta | O77: descartar | P77: religioso | Q77: devocional-diario | R77: 27 | S77: 27 | T77: 0.85 | U77: desconhecido | V77: 0 | W77: 1 | X77: 2026-08-21 | Y77: 2026-08-21 | Z77: ebook | AA77: nao | AB77: Oferta | AC77: 4 | AD77: 7 | AE77: 10 | AF77: 3 | AH77: # Desafio 21 Dias com Deus (Traco Home)
A78: Biblioteca do Concurseiro | B78: =MIN(10, IF(N78="ativa",5,IF(N78="nova",4,IF(N78="esfriando",2,0)))+IF(L78>=9,3,IF(L78>=3,2,IF(L78>=1,1,0)))+IF(M78>=60,1.5,IF(M78>=30,1,IF(M78>=14,0.5,0)))+IF(V78>=50,1.5,IF(V78>=10,1,IF(V78>=1,0.5,0)))+IF(W78>=4,0.5,0)) -> 0.5 | C78: =ROUND(AC78*0.15+AD78*0.25+AE78*0.4+AF78*0.2,1) -> 6.4 | D78: =ROUND(B78*0.45+C78*0.55,1) -> 3.7 | E78: =IF(D78>=7,"Alta",IF(D78>=5,"Media","Baixa")) -> Baixa | F78: bibliotecadoconcurseiro.site | G78: 1 | H78: acervo-pdf | I78: 1 | J78: abrir pagina | K78: buscar na biblioteca | L78: 0 | M78: 0 | N78: morta | O78: observar | P78: concursos | Q78: acervo-pdf | R78: 0 | S78: 27 | T78: 0.9 | U78: hotmart | V78: 5 | W78: 1 | X78: 2026-08-20 | Y78: 2026-08-20 | Z78: pdf | AA78: nao | AB78: Oferta | AC78: 3 | AD78: 7 | AE78: 9 | AF78: 3 | AH78: # Biblioteca do Concurseiro
A79: Ângulo — Criança que não aprende a ler | B79: =MIN(10, IF(N79="ativa",5,IF(N79="nova",4,IF(N79="esfriando",2,0)))+IF(L79>=9,3,IF(L79>=3,2,IF(L79>=1,1,0)))+IF(M79>=60,1.5,IF(M79>=30,1,IF(M79>=14,0.5,0)))+IF(V79>=50,1.5,IF(V79>=10,1,IF(V79>=1,0.5,0)))+IF(W79>=4,0.5,0)) -> 0.5 | C79: =ROUND(AC79*0.15+AD79*0.25+AE79*0.4+AF79*0.2,1) -> 6.4 | D79: =ROUND(B79*0.45+C79*0.55,1) -> 3.7 | E79: =IF(D79>=7,"Alta",IF(D79>=5,"Media","Baixa")) -> Baixa | F79: busca: alfabetização em casa | G79: 1 | H79: alfabetizacao | I79: 4 | J79: — | K79: buscar na biblioteca | L79: 0 | M79: 0 | N79: morta | O79: observar | P79: comportamento-infantil | Q79: alfabetizacao | R79: 9 | S79: 35 | T79: 0.94 | U79: hotmart | V79: 2 | W79: 1 | X79: 2026-08-21 | Y79: 2026-08-21 | Z79: pdf, curso | AA79: nao | AB79: Angulo | AC79: 4 | AD79: 7 | AE79: 8 | AF79: 4 | AH79: # Ângulo — Alfabetização em casa
A80: App do Paizão | B80: =MIN(10, IF(N80="ativa",5,IF(N80="nova",4,IF(N80="esfriando",2,0)))+IF(L80>=9,3,IF(L80>=3,2,IF(L80>=1,1,0)))+IF(M80>=60,1.5,IF(M80>=30,1,IF(M80>=14,0.5,0)))+IF(V80>=50,1.5,IF(V80>=10,1,IF(V80>=1,0.5,0)))+IF(W80>=4,0.5,0)) -> 2.5 | C80: =ROUND(AC80*0.15+AD80*0.25+AE80*0.4+AF80*0.2,1) -> 4.6 | D80: =ROUND(B80*0.45+C80*0.55,1) -> 3.7 | E80: =IF(D80>=7,"Alta",IF(D80>=5,"Media","Baixa")) -> Baixa | F80: busca: app do paizão | G80: 1 | H80: fitness-paternidade | I80: 1 | J80: — | K80: buscar na biblioteca | L80: 0 | M80: 0 | N80: esfriando | O80: observar | P80: saude-estetica-fitness | Q80: fitness-paternidade | R80: 50 | S80: 120 | T80: 0.85 | U80: kirvano | V80: 2 | W80: 3 | X80: 2026-08-21 | Y80: 2026-08-23 | Z80: app, comunidade | AA80: sim | AB80: Oferta | AC80: 9 | AD80: 5 | AE80: 3 | AF80: 4 | AH80: # App do Paizão
A81: Desafio de treino com loop de anamnese (nome nao capturado) | B81: =MIN(10, IF(N81="ativa",5,IF(N81="nova",4,IF(N81="esfriando",2,0)))+IF(L81>=9,3,IF(L81>=3,2,IF(L81>=1,1,0)))+IF(M81>=60,1.5,IF(M81>=30,1,IF(M81>=14,0.5,0)))+IF(V81>=50,1.5,IF(V81>=10,1,IF(V81>=1,0.5,0)))+IF(W81>=4,0.5,0)) -> 2.5 | C81: =ROUND(AC81*0.15+AD81*0.25+AE81*0.4+AF81*0.2,1) -> 4.7 | D81: =ROUND(B81*0.45+C81*0.55,1) -> 3.7 | E81: =IF(D81>=7,"Alta",IF(D81>=5,"Media","Baixa")) -> Baixa | F81: busca: desafio treino plano alimentar anamnese | G81: 1 | H81: desafio-com-funil-de-anamnese | I81: 1 | J81: — | K81: buscar na biblioteca | L81: 0 | M81: 0 | N81: esfriando | O81: observar | P81: saude-estetica-fitness | Q81: desafio-com-funil-de-anamnese | R81: 0 | S81: 150 | T81: 0.8 | U81: lastlink | V81: 1 | W81: 3 | X81: 2026-08-23 | Y81: 2026-08-27 | Z81: planilha | AA81: nao | AB81: Oferta | AC81: 10 | AD81: 4 | AE81: 3 | AF81: 5 | AH81: # Desafio de treino com loop de anamnese (nome nao capturado)
A82: Ângulo — Pare de gritar com seu filho | B82: =MIN(10, IF(N82="ativa",5,IF(N82="nova",4,IF(N82="esfriando",2,0)))+IF(L82>=9,3,IF(L82>=3,2,IF(L82>=1,1,0)))+IF(M82>=60,1.5,IF(M82>=30,1,IF(M82>=14,0.5,0)))+IF(V82>=50,1.5,IF(V82>=10,1,IF(V82>=1,0.5,0)))+IF(W82>=4,0.5,0)) -> 0 | C82: =ROUND(AC82*0.15+AD82*0.25+AE82*0.4+AF82*0.2,1) -> 6.8 | D82: =ROUND(B82*0.45+C82*0.55,1) -> 3.7 | E82: =IF(D82>=7,"Alta",IF(D82>=5,"Media","Baixa")) -> Baixa | F82: busca: parar de gritar filho | G82: 1 | H82: birra-disciplina | I82: 5 | J82: — | K82: buscar na biblioteca | L82: 0 | M82: 0 | N82: morta | O82: replicar | P82: comportamento-infantil | Q82: birra-disciplina | R82: 0 | S82: 37 | T82: 0.9 | U82: desconhecido | V82: 0 | W82: 1 | X82: 2026-08-21 | Y82: 2026-08-21 | Z82: ebook | AA82: nao | AB82: Angulo | AC82: 4 | AD82: 7 | AE82: 9 | AF82: 4 | AH82: # Ângulo — Pare de gritar
A83: Desafio de 30 Dias com Deus | B83: =MIN(10, IF(N83="ativa",5,IF(N83="nova",4,IF(N83="esfriando",2,0)))+IF(L83>=9,3,IF(L83>=3,2,IF(L83>=1,1,0)))+IF(M83>=60,1.5,IF(M83>=30,1,IF(M83>=14,0.5,0)))+IF(V83>=50,1.5,IF(V83>=10,1,IF(V83>=1,0.5,0)))+IF(W83>=4,0.5,0)) -> 0 | C83: =ROUND(AC83*0.15+AD83*0.25+AE83*0.4+AF83*0.2,1) -> 6.7 | D83: =ROUND(B83*0.45+C83*0.55,1) -> 3.7 | E83: =IF(D83>=7,"Alta",IF(D83>=5,"Media","Baixa")) -> Baixa | F83: desafio30diascomdeus.online | G83: 1 | H83: devocional-diario | I83: 3 | J83: abrir pagina | K83: buscar na biblioteca | L83: 0 | M83: 0 | N83: morta | O83: descartar | P83: religioso | Q83: devocional-diario | R83: 29.9 | S83: 29.9 | T83: 0.85 | U83: cakto | V83: 0 | W83: 1 | X83: 2026-08-21 | Y83: 2026-08-21 | Z83: ebook | AA83: nao | AB83: Oferta | AC83: 4 | AD83: 6 | AE83: 10 | AF83: 3 | AH83: # Desafio de 30 Dias com Deus
A84: Guia de Desintoxicação Digital — @vidasemtela | B84: =MIN(10, IF(N84="ativa",5,IF(N84="nova",4,IF(N84="esfriando",2,0)))+IF(L84>=9,3,IF(L84>=3,2,IF(L84>=1,1,0)))+IF(M84>=60,1.5,IF(M84>=30,1,IF(M84>=14,0.5,0)))+IF(V84>=50,1.5,IF(V84>=10,1,IF(V84>=1,0.5,0)))+IF(W84>=4,0.5,0)) -> 0 | C84: =ROUND(AC84*0.15+AD84*0.25+AE84*0.4+AF84*0.2,1) -> 6.8 | D84: =ROUND(B84*0.45+C84*0.55,1) -> 3.7 | E84: =IF(D84>=7,"Alta",IF(D84>=5,"Media","Baixa")) -> Baixa | F84: ebook.desintoxicacaodigital.com.br | G84: 1 | H84: telas | I84: 2 | J84: abrir pagina | K84: buscar na biblioteca | L84: 0 | M84: 0 | N84: morta | O84: replicar | P84: comportamento-infantil | Q84: telas | R84: 19.9 | S84: 20 | T84: 0.92 | U84: kiwify | V84: 0 | W84: 1 | X84: 2026-08-21 | Y84: 2026-08-21 | Z84: ebook | AA84: nao | AB84: Oferta | AC84: 2 | AD84: 5 | AE84: 9 | AF84: 8 | AH84: # Guia de Desintoxicação Digital
... A124: Revenda de assinatura CapCut Pro | B124: =MIN(10, IF(N124="ativa",5,IF(N124="nova",4,IF(N124="esfriando",2,0)))+IF(L124>=9,3,IF(L124>=3,2,IF(L124>=1,1,0)))+IF(M124>=60,1.5,IF(M124>=30,1,IF(M124>=14,0.5,0)))+IF(V124>=50,1.5,IF(V124>=10,1,IF(V124>=1,0.5,0)))+IF(W124>=4,0.5,0)) -> 2.5 | C124: =ROUND(AC124*0.15+AD124*0.25+AE124*0.4+AF124*0.2,1) -> 2 | D124: =ROUND(B124*0.45+C124*0.55,1) -> 2.2 | E124: =IF(D124>=7,"Alta",IF(D124>=5,"Media","Baixa")) -> Baixa | F124: busca: CapCut Pro assinatura barata | G124: 1 | H124: revenda-assinatura-alheia | I124: 1 | J124: — | K124: buscar na biblioteca | L124: 0 | M124: 0 | N124: esfriando | O124: descartar | P124: ferramentas-ia-edicao | Q124: revenda-assinatura-alheia | R124: 0 | S124: 0 | T124: 0.7 | U124: kirvano | V124: 1 | W124: 2 | X124: 2026-08-24 | Y124: 2026-08-27 | Z124: app | AA124: nao | AB124: Oferta | AC124: 0 | AD124: 3 | AE124: 2 | AF124: 2 | AH124: # Revenda de assinatura CapCut Pro

Sheet Grupos
A1: AGRUPAMENTOS — quem aponta pro mesmo lugar e quem esta vendendo a mesma coisa
A3: 1. Mesma oferta / mesmo angulo (clusters com 2 ou mais)
A4: Cluster | B4: Ofertas | C4: Nota geral (max) | D4: Nota geral (media) | E4: Criativos ativos (soma) | F4: Quais ofertas
A5: birra-disciplina | B5: 5 | C5: 3.8 | D5: =IFERROR(ROUND(AVERAGEIF(Ofertas!$H$2:$H$124,$A5,Ofertas!$D$2:$D$124),1),"") -> 3.5 | E5: =SUMIF(Ofertas!$H$2:$H$124,$A5,Ofertas!$L$2:$L$124) -> 0 | F5: Ângulo — Birra, teimosia e filho que não obedece | Ângulo — Pare de gritar com seu filho | Domando a Teimosia | Disciplina Positiva em Casa — eBook + 40 modelos de rotina | Pare de Gritar com seu Filho — Bia Arcangeli
A6: imprimivel-brincadeira | B6: 4 | C6: 7.4 | D6: =IFERROR(ROUND(AVERAGEIF(Ofertas!$H$2:$H$124,$A6,Ofertas!$D$2:$D$124),1),"") -> 6.3 | E6: =SUMIF(Ofertas!$H$2:$H$124,$A6,Ofertas!$L$2:$L$124) -> 12 | F6: +150 Bonecas de Papel — Maria Criativa | Casinha dos Sonhos — casinha de papel imprimivel | Kit Mundinho de Papel | Angulo — bonecas e cenarios de papel imprimiveis
A7: caligrafia | B7: 4 | C7: 7.1 | D7: =IFERROR(ROUND(AVERAGEIF(Ofertas!$H$2:$H$124,$A7,Ofertas!$D$2:$D$124),1),"") -> 6 | E7: =SUMIF(Ofertas!$H$2:$H$124,$A7,Ofertas!$L$2:$L$124) -> 10 | F7: Colecao Completa de Caligrafia 1o ao 6o ano — 380 atividades | Caderno Completo de Caligrafia — +300 atividades | Kit Do Rabisco a Letra Bonita — Uiara Oliveira | Angulo — caligrafia e grafismo imprimivel
A8: alfabetizacao | B8: 4 | C8: 6.9 | D8: =IFERROR(ROUND(AVERAGEIF(Ofertas!$H$2:$H$124,$A8,Ofertas!$D$2:$D$124),1),"") -> 5.2 | E8: =SUMIF(Ofertas!$H$2:$H$124,$A8,Ofertas!$L$2:$L$124) -> 12 | F8: Kit Grafismo Fonetico — Leitura Facil | Kit de Alfabetizacao Alfa Kids — 2.750 atividades | Ângulo — Criança que não aprende a ler | Método NeuroOctoMusical (Pipo) — alfabetização por sílabas
A9: taxa-para-liberar-certificado | B9: 4 | C9: 6.1 | D9: =IFERROR(ROUND(AVERAGEIF(Ofertas!$H$2:$H$124,$A9,Ofertas!$D$2:$D$124),1),"") -> 5.6 | E9: =SUMIF(Ofertas!$H$2:$H$124,$A9,Ofertas!$L$2:$L$124) -> 0 | F9: Cursos Gratis Online | Certificado Curso Online — curso gratis, certificado R$ 139,90 | Certifica Brasil — prova online, certificado pago | Angulo — curso gratis, certificado pago
A10: retrato-alma-gemea | B10: 3 | C10: 7.2 | D10: =IFERROR(ROUND(AVERAGEIF(Ofertas!$H$2:$H$124,$A10,Ofertas!$D$2:$D$124),1),"") -> 6.2 | E10: =SUMIF(Ofertas!$H$2:$H$124,$A10,Ofertas!$L$2:$L$124) -> 0 | F10: Retrato da Alma Gemea | The Soulmate Sketcher | Angulo - Quiz de 60s que gera o retrato
A11: taxa-para-liberar | B11: 3 | C11: 6 | D11: =IFERROR(ROUND(AVERAGEIF(Ofertas!$H$2:$H$124,$A11,Ofertas!$D$2:$D$124),1),"") -> 4.8 | E11: =SUMIF(Ofertas!$H$2:$H$124,$A11,Ofertas!$L$2:$L$124) -> 0 | F11: Google Captcha (TW Empreendimentos Digitais) | Escada de taxas decrescentes no pos-compra (nome nao capturado) | Love Pix
A12: danca-gospel-ministerio | B12: 3 | C12: 5.8 | D12: =IFERROR(ROUND(AVERAGEIF(Ofertas!$H$2:$H$124,$A12,Ofertas!$D$2:$D$124),1),"") -> 5.5 | E12: =SUMIF(Ofertas!$H$2:$H$124,$A12,Ofertas!$L$2:$L$124) -> 6 | F12: Dicionario em Movimento — 90 movimentos para ministracao | Brumdance 3 em 1 — ballet, jazz e contemporaneo para ministrar | Movimentos de Adoracao — 40 coreografias gospel prontas
A13: tea-autismo | B13: 3 | C13: 3.9 | D13: =IFERROR(ROUND(AVERAGEIF(Ofertas!$H$2:$H$124,$A13,Ofertas!$D$2:$D$124),1),"") -> 3.5 | E13: =SUMIF(Ofertas!$H$2:$H$124,$A13,Ofertas!$L$2:$L$124) -> 0 | F13: Ângulo — Kit imprimível para criança com TEA | Kit Só Escola Autismo — 650 páginas, 11 apostilas | TEA Sem Crise — Dr. Fábio Coelho
A14: devocional-diario | B14: 3 | C14: 3.9 | D14: =IFERROR(ROUND(AVERAGEIF(Ofertas!$H$2:$H$124,$A14,Ofertas!$D$2:$D$124),1),"") -> 3.8 | E14: =SUMIF(Ofertas!$H$2:$H$124,$A14,Ofertas!$L$2:$L$124) -> 0 | F14: Desafio 21 Dias com Deus (clone .shop) | Desafio 21 Dias com Deus (Traco Home) | Desafio de 30 Dias com Deus
A15: material-para-professora-de-ballet | B15: 2 | C15: 6.6 | D15: =IFERROR(ROUND(AVERAGEIF(Ofertas!$H$2:$H$124,$A15,Ofertas!$D$2:$D$124),1),"") -> 6.1 | E15: =SUMIF(Ofertas!$H$2:$H$124,$A15,Ofertas!$L$2:$L$124) -> 13 | F15: Cantigas da Bailarina — repertorio pronto para Baby Class | 250 Dinamicas de Ballet Prontas para Professoras
A16: acervo-professora | B16: 2 | C16: 6.3 | D16: =IFERROR(ROUND(AVERAGEIF(Ofertas!$H$2:$H$124,$A16,Ofertas!$D$2:$D$124),1),"") -> 6.1 | E16: =SUMIF(Ofertas!$H$2:$H$124,$A16,Ofertas!$L$2:$L$124) -> 2 | F16: Clube da Pedagogia — kit 3.000+ atividades BNCC | Licao Kids — loja de atividades imprimiveis
... A24: cura-interior | B24: 2 | C24: 3.7 | D24: =IFERROR(ROUND(AVERAGEIF(Ofertas!$H$2:$H$124,$A24,Ofertas!$D$2:$D$124),1),"") -> 3.7 | E24: =SUMIF(Ofertas!$H$2:$H$124,$A24,Ofertas!$L$2:$L$124) -> 0 | F24: Cura da Alma — devocional diario para traumas e feridas | Devocional com Proposito para Mulheres — 30 Dias de Cura Interior
A26: 2. Mesmo link de destino (mesma pagina de vendas ou mesmo termo de anuncio)
A27: Grupo (destino) | B27: Ofertas | C27: Nota geral (max) | D27: Criativos ativos (soma) | E27: Quais ofertas | F27: Tipo de agrupamento
A28: hotmart.com | B28: 3 | C28: 3.7 | D28: =SUMIF(Ofertas!$F$2:$F$124,$A28,Ofertas!$L$2:$L$124) -> 0 | E28: Cura da Alma — devocional diario para traumas e feridas | Devocional 15 dias — Para quem sofre de ansiedade | Devocional com Proposito para Mulheres — 30 Dias de Cura Interior | F28: mesma pagina de vendas
A29: dancadosnoivosonline.com | B29: 1 | C29: 7.5 | D29: =SUMIF(Ofertas!$F$2:$F$124,$A29,Ofertas!$L$2:$L$124) -> 9 | E29: Danca dos Noivos Online | F29: mesma pagina de vendas
A30: bonecasdepapel28.lovable.app | B30: 1 | C30: 7.4 | D30: =SUMIF(Ofertas!$F$2:$F$124,$A30,Ofertas!$L$2:$L$124) -> 9 | E30: +150 Bonecas de Papel — Maria Criativa | F30: mesma pagina de vendas
A31: alldigital.fun | B31: 1 | C31: 7.2 | D31: =SUMIF(Ofertas!$F$2:$F$124,$A31,Ofertas!$L$2:$L$124) -> 0 | E31: Retrato da Alma Gemea | F31: mesma pagina de vendas
A32: atividade-cursiva.netlify.app | B32: 1 | C32: 7.1 | D32: =SUMIF(Ofertas!$F$2:$F$124,$A32,Ofertas!$L$2:$L$124) -> 8 | E32: Colecao Completa de Caligrafia 1o ao 6o ano — 380 atividades | F32: mesma pagina de vendas
A33: thelittlegenius.com.br | B33: 1 | C33: 7.1 | D33: =SUMIF(Ofertas!$F$2:$F$124,$A33,Ofertas!$L$2:$L$124) -> 1 | E33: Little Genius — Kit de 235+ atividades educativas | F33: mesma pagina de vendas
A34: busca: grafismo fonetico | B34: 1 | C34: 6.9 | D34: =SUMIF(Ofertas!$F$2:$F$124,$A34,Ofertas!$L$2:$L$124) -> 10 | E34: Kit Grafismo Fonetico — Leitura Facil | F34: mesmo termo na Biblioteca
A35: busca: missa em atividades | B35: 1 | C35: 6.8 | D35: =SUMIF(Ofertas!$F$2:$F$124,$A35,Ofertas!$L$2:$L$124) -> 3 | E35: Missa em Atividades — kit catolico infantil imprimivel | F35: mesmo termo na Biblioteca
A36: ballerinalab.com.br | B36: 1 | C36: 6.6 | D36: =SUMIF(Ofertas!$F$2:$F$124,$A36,Ofertas!$L$2:$L$124) -> 11 | E36: Cantigas da Bailarina — repertorio pronto para Baby Class | F36: mesma pagina de vendas
A37: busca: coreografias prontas | B37: 1 | C37: 6.6 | D37: =SUMIF(Ofertas!$F$2:$F$124,$A37,Ofertas!$L$2:$L$124) -> 19 | E37: Angulo — material pronto para quem ENSINA danca | F37: mesmo termo na Biblioteca
A38: casinhadossonhos.com.br | B38: 1 | C38: 6.5 | D38: =SUMIF(Ofertas!$F$2:$F$124,$A38,Ofertas!$L$2:$L$124) -> 2 | E38: Casinha dos Sonhos — casinha de papel imprimivel | F38: mesma pagina de vendas
A39: busca: alfa kids | B39: 1 | C39: 6.3 | D39: =SUMIF(Ofertas!$F$2:$F$124,$A39,Ofertas!$L$2:$L$124) -> 2 | E39: Kit de Alfabetizacao Alfa Kids — 2.750 atividades | F39: mesmo termo na Biblioteca
... A148: busca: CapCut Pro assinatura barata | B148: 1 | C148: 2.2 | D148: =SUMIF(Ofertas!$F$2:$F$124,$A148,Ofertas!$L$2:$L$124) -> 0 | E148: Revenda de assinatura CapCut Pro | F148: mesmo termo na Biblioteca

Sheet Criativos
A1: Oferta | B1: Anunciante | C1: ID do criativo | D1: Link do criativo | E1: Veiculacao iniciada | F1: Pagina de vendas | G1: Nota geral
A2: Danca dos Noivos Online | B2: Danca dos Noivos | C2: 1709135547148649 | D2: anuncio | E2: 15/04/2025 | F2: abrir | G2: 7.5
A3: Danca dos Noivos Online | B3: Danca dos Noivos | C3: 663145749976219 | D3: anuncio | E3: 15/04/2025 | F3: abrir | G3: 7.5
A4: Danca dos Noivos Online | B4: Danca dos Noivos | C4: 1428634915161518 | D4: anuncio | E4: 15/04/2025 | F4: abrir | G4: 7.5
A5: Danca dos Noivos Online | B5: Danca dos Noivos | C5: 1352349473058400 | D5: anuncio | E5: 07/11/2025 | F5: abrir | G5: 7.5
A6: Danca dos Noivos Online | B6: Danca dos Noivos | C6: 863407529970391 | D6: anuncio | E6: 11/12/2025 | F6: abrir | G6: 7.5
A7: Danca dos Noivos Online | B7: Danca dos Noivos | C7: 1435118811624847 | D7: anuncio | E7: 08/02/2026 | F7: abrir | G7: 7.5
A8: Danca dos Noivos Online | B8: Danca dos Noivos | C8: 1777067386338991 | D8: anuncio | E8: 01/07/2026 | F8: abrir | G8: 7.5
A9: Danca dos Noivos Online | B9: Danca dos Noivos | C9: 1080066974349178 | D9: anuncio | E9: 22/07/2026 | F9: abrir | G9: 7.5
A10: Danca dos Noivos Online | B10: Danca dos Noivos | C10: 1536715551263941 | D10: anuncio | E10: 22/07/2026 | F10: abrir | G10: 7.5
A11: +150 Bonecas de Papel — Maria Criativa | C11: — | D11: buscar na biblioteca | F11: abrir | G11: 7.4
A12: Retrato da Alma Gemea | C12: — | D12: buscar na biblioteca | F12: abrir | G12: 7.2
A13: Colecao Completa de Caligrafia 1o ao 6o ano — 380 atividades | C13: — | D13: buscar na biblioteca | F13: abrir | G13: 7.1
A14: Little Genius — Kit de 235+ atividades educativas | C14: — | D14: buscar na biblioteca | F14: abrir | G14: 7.1
A15: Kit Grafismo Fonetico — Leitura Facil | C15: — | D15: buscar na biblioteca | F15: — | G15: 6.9
A16: Missa em Atividades — kit catolico infantil imprimivel | C16: — | D16: buscar na biblioteca | F16: — | G16: 6.8
A17: Cantigas da Bailarina — repertorio pronto para Baby Class | B17: Ballerina Lab | C17: 1788079548857559 | D17: anuncio | E17: 28/08/2026 | F17: abrir | G17: 6.6
A18: Cantigas da Bailarina — repertorio pronto para Baby Class | B18: Ballerina Lab | C18: 2263316144514045 | D18: anuncio | E18: 28/08/2026 | F18: abrir | G18: 6.6
A19: Cantigas da Bailarina — repertorio pronto para Baby Class | B19: Ballerina Lab | C19: 1609143730696444 | D19: anuncio | E19: 28/08/2026 | F19: abrir | G19: 6.6
A20: Cantigas da Bailarina — repertorio pronto para Baby Class | B20: Ballerina Lab | C20: 1896609284648902 | D20: anuncio | E20: 28/08/2026 | F20: abrir | G20: 6.6
A21: Cantigas da Bailarina — repertorio pronto para Baby Class | B21: Ballerina Lab | C21: 941791291734829 | D21: anuncio | E21: 31/08/2026 | F21: abrir | G21: 6.6
A22: Cantigas da Bailarina — repertorio pronto para Baby Class | B22: Ballerina Lab | C22: 1244590731133551 | D22: anuncio | E22: 31/08/2026 | F22: abrir | G22: 6.6
A23: Cantigas da Bailarina — repertorio pronto para Baby Class | B23: Ballerina Lab | C23: 1588414766277941 | D23: anuncio | E23: 31/08/2026 | F23: abrir | G23: 6.6
A24: Cantigas da Bailarina — repertorio pronto para Baby Class | B24: Ballerina Lab | C24: 3969590060015031 | D24: anuncio | E24: 01/09/2026 | F24: abrir | G24: 6.6
A25: Cantigas da Bailarina — repertorio pronto para Baby Class | B25: Ballerina Lab | C25: 3469711586522153 | D25: anuncio | E25: 01/09/2026 | F25: abrir | G25: 6.6
A26: Cantigas da Bailarina — repertorio pronto para Baby Class | B26: Ballerina Lab | C26: 1808375023485352 | D26: anuncio | E26: 01/09/2026 | F26: abrir | G26: 6.6
A27: Cantigas da Bailarina — repertorio pronto para Baby Class | B27: Ballerina Lab | C27: 2501108650313455 | D27: anuncio | E27: 02/09/2026 | F27: abrir | G27: 6.6
A28: Angulo — material pronto para quem ENSINA danca | C28: — | D28: buscar na biblioteca | F28: — | G28: 6.6
A29: Casinha dos Sonhos — casinha de papel imprimivel | B29: Prof.a Juliana Gamon | C29: — | D29: buscar na biblioteca | F29: abrir | G29: 6.5
A30: Kit de Alfabetizacao Alfa Kids — 2.750 atividades | C30: — | D30: buscar na biblioteca | F30: — | G30: 6.3
A31: Clube da Pedagogia — kit 3.000+ atividades BNCC | C31: — | D31: buscar na biblioteca | F31: abrir | G31: 6.3
A32: Combo 10 Cursos de Danca do Ventre — Patricia Cavalcante | B32: Patricia Cavalcante | C32: 917257397128811 | D32: anuncio | E32: 30/01/2025 | F32: abrir | G32: 6.2
A33: Combo 10 Cursos de Danca do Ventre — Patricia Cavalcante | B33: Patricia Cavalcante | C33: 1023550673675761 | D33: anuncio | E33: 29/05/2026 | F33: abrir | G33: 6.2
A34: Portal Shakti Club — bellydance e tribal fusion | B34: Luma Shakti Studio Online | C34: 1481713799929612 | D34: anuncio | E34: 17/06/2026 | F34: abrir | G34: 6.2
A35: Portal Shakti Club — bellydance e tribal fusion | B35: Luma Shakti Studio Online | C35: 1435958288287540 | D35: anuncio | E35: 22/06/2026 | F35: abrir | G35: 6.2
A36: Portal Shakti Club — bellydance e tribal fusion | B36: Luma Shakti Studio Online | C36: 1622766862154166 | D36: anuncio | E36: 22/06/2026 | F36: abrir | G36: 6.2
A37: Kit Mundinho de Papel | C37: — | D37: buscar na biblioteca | F37: abrir | G37: 6.1
A38: Tutu da Ju — assinatura de ballet classico online | B38: Tutu da Ju | C38: 1354322349865514 | D38: anuncio | E38: 22/04/2026 | F38: abrir | G38: 6.1
A39: Cursos Gratis Online | C39: — | D39: buscar na biblioteca | F39: abrir | G39: 6.1
A40: Google Captcha (TW Empreendimentos Digitais) | C40: — | D40: buscar na biblioteca | F40: — | G40: 6
A41: Alfabetinho — pacotes de atividades imprimiveis | C41: — | D41: buscar na biblioteca | F41: abrir | G41: 5.9
A42: Licao Kids — loja de atividades imprimiveis | C42: — | D42: buscar na biblioteca | F42: abrir | G42: 5.9
A43: Caderno Completo de Caligrafia — +300 atividades | C43: — | D43: buscar na biblioteca | F43: abrir | G43: 5.9
A44: Atelie Digital Pequenas Estilistas — Colecao 2027 | C44: — | D44: buscar na biblioteca | F44: abrir | G44: 5.9
A45: Escada de taxas decrescentes no pos-compra (nome nao capturado) | C45: — | D45: buscar na biblioteca | F45: — | G45: 5.8
A46: Dicionario em Movimento — 90 movimentos para ministracao | B46: Escola de Danca Louvor na Terra | C46: 1401478468587799 | D46: anuncio | E46: 25/08/2026 | F46: abrir | G46: 5.8
A47: Dicionario em Movimento — 90 movimentos para ministracao | B47: Escola de Danca Louvor na Terra | C47: 3514532285389014 | D47: anuncio | E47: 25/08/2026 | F47: abrir | G47: 5.8
A48: Dicionario em Movimento — 90 movimentos para ministracao | B48: Escola de Danca Louvor na Terra | C48: 1769707290732626 | D48: anuncio | E48: 31/08/2026 | F48: abrir | G48: 5.8
A49: Aerobico Ritmado — aula pronta com certificado de 50h | B49: Galera da EdFisica | C49: 1431162878924047 | D49: anuncio | E49: 27/08/2026 | F49: abrir | G49: 5.8
A50: Aerobico Ritmado — aula pronta com certificado de 50h | B50: Galera da EdFisica | C50: 2319243438820750 | D50: anuncio | E50: 27/08/2026 | F50: abrir | G50: 5.8
A51: Aerobico Ritmado — aula pronta com certificado de 50h | B51: Galera da EdFisica | C51: 2037174746939931 | D51: anuncio | E51: 27/08/2026 | F51: abrir | G51: 5.8
A52: The Soulmate Sketcher | C52: — | D52: buscar na biblioteca | F52: abrir | G52: 5.8
A53: Portal do MEI Brasil | C53: — | D53: buscar na biblioteca | F53: — | G53: 5.7
A54: Certificado Curso Online — curso gratis, certificado R$ 139,90 | C54: — | D54: buscar na biblioteca | F54: abrir | G54: 5.7
A55: Kit Do Rabisco a Letra Bonita — Uiara Oliveira | C55: — | D55: buscar na biblioteca | F55: — | G55: 5.6
A56: 250 Dinamicas de Ballet Prontas para Professoras | B56: Material da Prof | C56: 1388203450084932 | D56: anuncio | E56: 28/08/2026 | F56: abrir | G56: 5.4
A57: 250 Dinamicas de Ballet Prontas para Professoras | B57: Material da Prof | C57: 1326870229520439 | D57: anuncio | E57: 28/08/2026 | F57: abrir | G57: 5.4
A58: Angulo - Quiz de 60s que gera o retrato | C58: — | D58: buscar na biblioteca | F58: abrir | G58: 5.4
A59: Brumdance 3 em 1 — ballet, jazz e contemporaneo para ministrar | B59: Brumdance | C59: 1971523880902568 | D59: anuncio | E59: 07/08/2026 | F59: abrir | G59: 5.3
A60: Arquivos STL para impressao 3D | C60: — | D60: buscar na biblioteca | F60: — | G60: 5.3
A61: Angulo — bonecas e cenarios de papel imprimiveis | C61: — | D61: buscar na biblioteca | F61: — | G61: 5.3
A62: Angulo — caligrafia e grafismo imprimivel | C62: — | D62: buscar na biblioteca | F62: — | G62: 5.3
A63: Certifica Brasil — prova online, certificado pago | C63: — | D63: buscar na biblioteca | F63: — | G63: 5.3
A64: Movimentos de Adoracao — 40 coreografias gospel prontas | B64: Coreografias Gospel | C64: 1056884877074087 | D64: anuncio | E64: 02/09/2026 | F64: abrir | G64: 5.3
A65: Movimentos de Adoracao — 40 coreografias gospel prontas | B65: Coreografias Gospel | C65: 1442748831032425 | D65: anuncio | E65: 04/09/2026 | F65: abrir | G65: 5.3
A66: Angulo — curso gratis, certificado pago | C66: — | D66: buscar na biblioteca | F66: — | G66: 5.2
A67: Hinário em Movimento | C67: — | D67: buscar na biblioteca | F67: — | G67: 5.1
A68: Angulo — cobrar pelo servico publico que e gratuito | C68: — | D68: buscar na biblioteca | F68: — | G68: 5.1
A69: Music Creator Pro | C69: — | D69: buscar na biblioteca | F69: — | G69: 4.9
A70: Treino Trinca (Pedro Lotz) | C70: — | D70: buscar na biblioteca | F70: abrir | G70: 4.9
A71: Kit 1.000 Convites e Envelopes de Casamento (editáveis) | C71: — | D71: buscar na biblioteca | F71: — | G71: 4.8
A72: Unlovable | C72: — | D72: buscar na biblioteca | F72: — | G72: 4.8
A73: Curso de Massagem Tantrica (Wiapy) | C73: — | D73: buscar na biblioteca | F73: — | G73: 4.7
A74: Teacher ZAP — 7 idiomas pelo WhatsApp | C74: — | D74: buscar na biblioteca | F74: — | G74: 4.5
A75: Forrozeiro do Zero (nome comercial nao confirmado) | B75: matheuscasbri | C75: 1064507922644275 | D75: anuncio | E75: 29/08/2026 | F75: abrir | G75: 4.5
A76: Forrozeiro do Zero (nome comercial nao confirmado) | B76: matheuscasbri | C76: 1871711103791552 | D76: anuncio | E76: 29/08/2026 | F76: abrir | G76: 4.5
A77: INSTALADOR ROBÔ PRONTO 2.0 | C77: — | D77: buscar na biblioteca | F77: — | G77: 4.4
A78: +350 Bonecas de Papel — Papel Mágico | C78: — | D78: buscar na biblioteca | F78: abrir | G78: 4.4
A79: Forro do Zero — Pe Descalco | B79: Pe Descalco | C79: — | D79: buscar na biblioteca | F79: abrir | G79: 4.4
A80: Ângulo — Criança viciada em tela | C80: — | D80: buscar na biblioteca | F80: — | G80: 4.3
A81: App de orcamento para eletricista + imprimiveis | C81: — | D81: buscar na biblioteca | F81: — | G81: 4.3
A82: Artesanato, moldes e PDF criativo | C82: — | D82: buscar na biblioteca | F82: — | G82: 4.2
A83: Material pedagogico e apostilas imprimiveis | C83: — | D83: buscar na biblioteca | F83: — | G83: 4.2
A84: Ângulo — 'Será que meu filho tem...?' como isca de topo | C84: — | D84: buscar na biblioteca | F84: — | G84: 4.2
A85: Renderizador de imagem com recarga na Google (nome nao capturado) | C85: — | D85: buscar na biblioteca | F85: — | G85: 4.2
A86: Stalkeia.ai | C86: — | D86: buscar na biblioteca | F86: abrir | G86: 4.2
A87: AUKS VIP / AUKS BOT | C87: — | D87: buscar na biblioteca | F87: — | G87: 4.1
A88: Cafe Premium — Barista Academy | C88: — | D88: buscar na biblioteca | F88: — | G88: 4.1
A89: Foto com pet gerada por IA (Wiapy) | C89: — | D89: buscar na biblioteca | F89: — | G89: 4.1
A90: Magias Amorosas - Hoodoo | C90: — | D90: buscar na biblioteca | F90: — | G90: 4.1
A91: Parábolas Kids — 1.001 parábolas bíblicas para crianças | C91: — | D91: buscar na biblioteca | F91: abrir | G91: 4.1
... A152: Revenda de assinatura CapCut Pro | C152: — | D152: buscar na biblioteca | F152: — | G152: 2.2
